Workbook

Sheet DataSet
A1: Row ID | B1: Order ID | C1: Order Date | D1: Ship Date | E1: Ship Mode | F1: Customer ID | G1: Customer Name | H1: Segment | I1: Country | J1: City | K1: State | L1: Postal Code | M1: Region | N1: Product ID | O1: Category | P1: Sub-Category | Q1: Product Name | R1: Sales | S1: Quantity | T1: Discount | U1: Profit | V1: Ship Mode Imputed | W1: Segment Imputed | X1: City and State | Y1: Sub-Category Imputed | Z1: Sales price Imputed W category | AA1: Sales W Sub Category | AB1: Total Sales | AC1: Total Sales W Discount | AD1: Country Code | AE1: Order Year | AF1: Order ID2
A2: 1 | B2: CA-2016-152156 | C2: 42682 | D2: 42685 | E2: Second Class | F2: CG-12520 | G2: Claire Gute | H2: Consumer | I2: United States | J2: Henderson | K2: Kentucky | L2: 42420 | M2: South | N2: FUR-BO-10001798 | O2: Furniture | P2: Bookcases | Q2: Bush Somerset Collection Bookcase | R2: 261.96 | S2: 2 | T2: 0 | U2: 41.9136 | V2: =IF(ISBLANK(E2),"UNKNOWN",E2) -> Second Class | W2: =IF(ISBLANK(H2),"UNKNOWN",H2) -> Consumer | X2: =CONCATENATE(J2," - ",K2) -> Henderson - Kentucky | Y2: =IF(ISBLANK(P2),"UNKNOWN",P2) -> Bookcases | Z2: =IF(ISBLANK(R2),ROUND(AVERAGEIF($O$2:$O$600,O2,$R$2:$R$29),0),R2) -> 261.96 | AA2: =IF(ISBLANK(R2),ROUND(AVERAGEIF($Y$2:$Y$600,Y2,$R$2:$R$29),0),R2) -> 261.96 | AB2: =AA2*S2 -> 523.92 | AC2: =AB2*(1-T2) -> 523.92 | AD2: CA | AE2: =MID(B2,4,4) -> 2016 | AF2: =RIGHT(B2,6) -> 152156
A3: 2 | B3: CA-2016-152156 | C3: 42682 | D3: 42685 | E3: Second Class | F3: CG-12520 | G3: Claire Gute | H3: Consumer | I3: United States | J3: Henderson | K3: Kentucky | L3: 42420 | M3: South | N3: FUR-CH-10000454 | O3: Furniture | P3: Chairs | Q3: Hon Deluxe Fabric Upholstered Stacking Chairs, Rounded Back | R3: 731.94 | S3: 3 | T3: 0 | U3: 219.582 | V3: =IF(ISBLANK(E3),"UNKNOWN",E3) -> Second Class | W3: =IF(ISBLANK(H3),"UNKNOWN",H3) -> Consumer | X3: =CONCATENATE(J3," - ",K3) -> Henderson - Kentucky | Y3: =IF(ISBLANK(P3),"UNKNOWN",P3) -> Chairs | Z3: =IF(ISBLANK(R3),ROUND(AVERAGEIF($O$2:$O$600,O3,$R$2:$R$29),0),R3) -> 731.94 | AA3: =IF(ISBLANK(R3),ROUND(AVERAGEIF($Y$2:$Y$600,Y3,$R$2:$R$29),0),R3) -> 731.94 | AB3: =AA3*S3 -> 2195.82 | AC3: =AB3*(1-T3) -> 2195.82 | AD3: CA | AE3: =MID(B3,4,4) -> 2016 | AF3: =RIGHT(B3,6) -> 152156
A4: 3 | B4: CA-2016-138688 | C4: 42533 | D4: 42537 | E4: Second Class | F4: DV-13045 | G4: Darrin Van Huff | H4: Corporate | I4: United States | J4: Los Angeles | K4: California | L4: 90036 | M4: West | N4: OFF-LA-10000240 | O4: Office Supplies | P4: Labels | Q4: Self-Adhesive Address Labels for Typewriters by Universal | R4: 14.62 | S4: 2 | T4: 0 | U4: 6.8714 | V4: =IF(ISBLANK(E4),"UNKNOWN",E4) -> Second Class | W4: =IF(ISBLANK(H4),"UNKNOWN",H4) -> Corporate | X4: =CONCATENATE(J4," - ",K4) -> Los Angeles - California | Y4: =IF(ISBLANK(P4),"UNKNOWN",P4) -> Labels | Z4: =IF(ISBLANK(R4),ROUND(AVERAGEIF($O$2:$O$600,O4,$R$2:$R$29),0),R4) -> 14.62 | AA4: =IF(ISBLANK(R4),ROUND(AVERAGEIF($Y$2:$Y$600,Y4,$R$2:$R$29),0),R4) -> 14.62 | AB4: =AA4*S4 -> 29.24 | AC4: =AB4*(1-T4) -> 29.24 | AD4: CA | AE4: =MID(B4,4,4) -> 2016 | AF4: =RIGHT(B4,6) -> 138688
A5: 4 | B5: US-2015-108966 | C5: 42288 | D5: 42295 | E5: Standard Class | F5: SO-20335 | G5: Sean O'Donnell | H5: Consumer | I5: United States | J5: Fort Lauderdale | K5: Florida | L5: 33311 | M5: South | N5: FUR-TA-10000577 | O5: Furniture | P5: Tables | Q5: Bretford CR4500 Series Slim Rectangular Table | R5: 957.5775 | S5: 5 | T5: 0.45 | U5: -383.031 | V5: =IF(ISBLANK(E5),"UNKNOWN",E5) -> Standard Class | W5: =IF(ISBLANK(H5),"UNKNOWN",H5) -> Consumer | X5: =CONCATENATE(J5," - ",K5) -> Fort Lauderdale - Florida | Y5: =IF(ISBLANK(P5),"UNKNOWN",P5) -> Tables | Z5: =IF(ISBLANK(R5),ROUND(AVERAGEIF($O$2:$O$600,O5,$R$2:$R$29),0),R5) -> 957.5775 | AA5: =IF(ISBLANK(R5),ROUND(AVERAGEIF($Y$2:$Y$600,Y5,$R$2:$R$29),0),R5) -> 957.5775 | AB5: =AA5*S5 -> 4787.8875 | AC5: =AB5*(1-T5) -> 2633.3381 | AD5: US | AE5: =MID(B5,4,4) -> 2015 | AF5: =RIGHT(B5,6) -> 108966
A6: 5 | B6: US-2015-108966 | C6: 42288 | D6: 42295 | E6: Standard Class | F6: SO-20335 | G6: Sean O'Donnell | H6: Consumer | I6: United States | J6: Fort Lauderdale | K6: Florida | L6: 33311 | M6: South | N6: OFF-ST-10000760 | O6: Office Supplies | P6: Storage | Q6: Eldon Fold 'N Roll Cart System | R6: 22.368 | S6: 2 | T6: 0.2 | U6: 2.5164 | V6: =IF(ISBLANK(E6),"UNKNOWN",E6) -> Standard Class | W6: =IF(ISBLANK(H6),"UNKNOWN",H6) -> Consumer | X6: =CONCATENATE(J6," - ",K6) -> Fort Lauderdale - Florida | Y6: =IF(ISBLANK(P6),"UNKNOWN",P6) -> Storage | Z6: =IF(ISBLANK(R6),ROUND(AVERAGEIF($O$2:$O$600,O6,$R$2:$R$29),0),R6) -> 22.368 | AA6: =IF(ISBLANK(R6),ROUND(AVERAGEIF($Y$2:$Y$600,Y6,$R$2:$R$29),0),R6) -> 22.368 | AB6: =AA6*S6 -> 44.736 | AC6: =AB6*(1-T6) -> 35.7888 | AD6: US | AE6: =MID(B6,4,4) -> 2015 | AF6: =RIGHT(B6,6) -> 108966
A7: 6 | B7: CA-2014-115812 | C7: 41799 | D7: 41804 | E7: Standard Class | F7: BH-11710 | G7: Brosina Hoffman | H7: Consumer | I7: United States | J7: Los Angeles | K7: California | L7: 90032 | M7: West | N7: FUR-FU-10001487 | O7: Furniture | P7: Furnishings | Q7: Eldon Expressions Wood and Plastic Desk Accessories, Cherry Wood | R7: 48.86 | S7: 7 | T7: 0 | U7: 14.1694 | V7: =IF(ISBLANK(E7),"UNKNOWN",E7) -> Standard Class | W7: =IF(ISBLANK(H7),"UNKNOWN",H7) -> Consumer | X7: =CONCATENATE(J7," - ",K7) -> Los Angeles - California | Y7: =IF(ISBLANK(P7),"UNKNOWN",P7) -> Furnishings | Z7: =IF(ISBLANK(R7),ROUND(AVERAGEIF($O$2:$O$600,O7,$R$2:$R$29),0),R7) -> 48.86 | AA7: =IF(ISBLANK(R7),ROUND(AVERAGEIF($Y$2:$Y$600,Y7,$R$2:$R$29),0),R7) -> 48.86 | AB7: =AA7*S7 -> 342.02 | AC7: =AB7*(1-T7) -> 342.02 | AD7: CA | AE7: =MID(B7,4,4) -> 2014 | AF7: =RIGHT(B7,6) -> 115812
A8: 7 | B8: CA-2014-115812 | C8: 41799 | D8: 41804 | E8: Standard Class | F8: BH-11710 | G8: Brosina Hoffman | H8: Consumer | I8: United States | J8: Los Angeles | K8: California | L8: 90032 | M8: West | N8: OFF-AR-10002833 | O8: Office Supplies | P8: Art | Q8: Newell 322 | R8: 7.28 | S8: 4 | T8: 0 | U8: 1.9656 | V8: =IF(ISBLANK(E8),"UNKNOWN",E8) -> Standard Class | W8: =IF(ISBLANK(H8),"UNKNOWN",H8) -> Consumer | X8: =CONCATENATE(J8," - ",K8) -> Los Angeles - California | Y8: =IF(ISBLANK(P8),"UNKNOWN",P8) -> Art | Z8: =IF(ISBLANK(R8),ROUND(AVERAGEIF($O$2:$O$600,O8,$R$2:$R$29),0),R8) -> 7.28 | AA8: =IF(ISBLANK(R8),ROUND(AVERAGEIF($Y$2:$Y$600,Y8,$R$2:$R$29),0),R8) -> 7.28 | AB8: =AA8*S8 -> 29.12 | AC8: =AB8*(1-T8) -> 29.12 | AD8: CA | AE8: =MID(B8,4,4) -> 2014 | AF8: =RIGHT(B8,6) -> 115812
A9: 8 | B9: CA-2014-115812 | C9: 41799 | D9: 41804 | E9: Standard Class | F9: BH-11710 | G9: Brosina Hoffman | H9: Consumer | I9: United States | J9: Los Angeles | K9: California | L9: 90032 | M9: West | N9: TEC-PH-10002275 | O9: Technology | P9: Phones | Q9: Mitel 5320 IP Phone VoIP phone | R9: 907.152 | S9: 6 | T9: 0.2 | U9: 90.7152 | V9: =IF(ISBLANK(E9),"UNKNOWN",E9) -> Standard Class | W9: =IF(ISBLANK(H9),"UNKNOWN",H9) -> Consumer | X9: =CONCATENATE(J9," - ",K9) -> Los Angeles - California | Y9: =IF(ISBLANK(P9),"UNKNOWN",P9) -> Phones | Z9: =IF(ISBLANK(R9),ROUND(AVERAGEIF($O$2:$O$600,O9,$R$2:$R$29),0),R9) -> 907.152 | AA9: =IF(ISBLANK(R9),ROUND(AVERAGEIF($Y$2:$Y$600,Y9,$R$2:$R$29),0),R9) -> 907.152 | AB9: =AA9*S9 -> 5442.912 | AC9: =AB9*(1-T9) -> 4354.3296 | AD9: CA | AE9: =MID(B9,4,4) -> 2014 | AF9: =RIGHT(B9,6) -> 115812
A10: 9 | B10: CA-2014-115812 | C10: 41799 | D10: 41804 | E10: Standard Class | F10: BH-11710 | G10: Brosina Hoffman | H10: Consumer | I10: United States | J10: Los Angeles | K10: California | L10: 90032 | M10: West | N10: OFF-BI-10003910 | O10: Office Supplies | P10: Binders | Q10: DXL Angle-View Binders with Locking Rings by Samsill | R10: 18.504 | S10: 3 | T10: 0.2 | U10: 5.7825 | V10: =IF(ISBLANK(E10),"UNKNOWN",E10) -> Standard Class | W10: =IF(ISBLANK(H10),"UNKNOWN",H10) -> Consumer | X10: =CONCATENATE(J10," - ",K10) -> Los Angeles - California | Y10: =IF(ISBLANK(P10),"UNKNOWN",P10) -> Binders | Z10: =IF(ISBLANK(R10),ROUND(AVERAGEIF($O$2:$O$600,O10,$R$2:$R$29),0),R10) -> 18.504 | AA10: =IF(ISBLANK(R10),ROUND(AVERAGEIF($Y$2:$Y$600,Y10,$R$2:$R$29),0),R10) -> 18.504 | AB10: =AA10*S10 -> 55.512 | AC10: =AB10*(1-T10) -> 44.4096 | AD10: CA | AE10: =MID(B10,4,4) -> 2014 | AF10: =RIGHT(B10,6) -> 115812
A11: 10 | B11: CA-2014-115812 | C11: 41799 | D11: 41804 | E11: Standard Class | F11: BH-11710 | G11: Brosina Hoffman | H11: Consumer | I11: United States | J11: Los Angeles | K11: California | L11: 90032 | M11: West | N11: OFF-AP-10002892 | O11: Office Supplies | P11: Appliances | Q11: Belkin F5C206VTEL 6 Outlet Surge | R11: 114.9 | S11: 5 | T11: 0 | U11: 34.47 | V11: =IF(ISBLANK(E11),"UNKNOWN",E11) -> Standard Class | W11: =IF(ISBLANK(H11),"UNKNOWN",H11) -> Consumer | X11: =CONCATENATE(J11," - ",K11) -> Los Angeles - California | Y11: =IF(ISBLANK(P11),"UNKNOWN",P11) -> Appliances | Z11: =IF(ISBLANK(R11),ROUND(AVERAGEIF($O$2:$O$600,O11,$R$2:$R$29),0),R11) -> 114.9 | AA11: =IF(ISBLANK(R11),ROUND(AVERAGEIF($Y$2:$Y$600,Y11,$R$2:$R$29),0),R11) -> 114.9 | AB11: =AA11*S11 -> 574.5 | AC11: =AB11*(1-T11) -> 574.5 | AD11: CA | AE11: =MID(B11,4,4) -> 2014 | AF11: =RIGHT(B11,6) -> 115812
A12: 11 | B12: CA-2014-115812 | C12: 41799 | D12: 41804 | E12: Standard Class | F12: BH-11710 | G12: Brosina Hoffman | H12: Consumer | I12: United States | J12: Los Angeles | K12: California | L12: 90032 | M12: West | N12: FUR-TA-10001539 | O12: Furniture | P12: Tables | Q12: Chromcraft Rectangular Conference Tables | R12: 1706.184 | S12: 9 | T12: 0.2 | U12: 85.3092 | V12: =IF(ISBLANK(E12),"UNKNOWN",E12) -> Standard Class | W12: =IF(ISBLANK(H12),"UNKNOWN",H12) -> Consumer | X12: =CONCATENATE(J12," - ",K12) -> Los Angeles - California | Y12: =IF(ISBLANK(P12),"UNKNOWN",P12) -> Tables | Z12: =IF(ISBLANK(R12),ROUND(AVERAGEIF($O$2:$O$600,O12,$R$2:$R$29),0),R12) -> 1706.184 | AA12: =IF(ISBLANK(R12),ROUND(AVERAGEIF($Y$2:$Y$600,Y12,$R$2:$R$29),0),R12) -> 1706.184 | AB12: =AA12*S12 -> 15355.656 | AC12: =AB12*(1-T12) -> 12284.525 | AD12: CA | AE12: =MID(B12,4,4) -> 2014 | AF12: =RIGHT(B12,6) -> 115812
A13: 12 | B13: CA-2014-115812 | C13: 41799 | D13: 41804 | E13: Standard Class | F13: BH-11710 | G13: Brosina Hoffman | H13: Consumer | I13: United States | J13: Los Angeles | K13: California | L13: 90032 | M13: West | N13: TEC-PH-10002033 | O13: Technology | P13: Phones | Q13: Konftel 250 Conference phone - Charcoal black | R13: 911.424 | S13: 4 | T13: 0.2 | U13: 68.3568 | V13: =IF(ISBLANK(E13),"UNKNOWN",E13) -> Standard Class | W13: =IF(ISBLANK(H13),"UNKNOWN",H13) -> Consumer | X13: =CONCATENATE(J13," - ",K13) -> Los Angeles - California | Y13: =IF(ISBLANK(P13),"UNKNOWN",P13) -> Phones | Z13: =IF(ISBLANK(R13),ROUND(AVERAGEIF($O$2:$O$600,O13,$R$2:$R$29),0),R13) -> 911.424 | AA13: =IF(ISBLANK(R13),ROUND(AVERAGEIF($Y$2:$Y$600,Y13,$R$2:$R$29),0),R13) -> 911.424 | AB13: =AA13*S13 -> 3645.696 | AC13: =AB13*(1-T13) -> 2916.5568 | AD13: CA | AE13: =MID(B13,4,4) -> 2014 | AF13: =RIGHT(B13,6) -> 115812
... A15: 14 | B15: CA-2016-161389 | C15: 42709 | D15: 42714 | E15: Standard Class | F15: IM-15070 | G15: Irene Maddox | H15: Consumer | I15: United States | J15: Seattle | K15: Washington | L15: 98103 | M15: West | N15: OFF-BI-10003656 | O15: Office Supplies | P15: Binders | Q15: Fellowes PB200 Plastic Comb Binding Machine | R15: 407.976 | S15: 3 | T15: 0.2 | U15: 132.5922 | V15: =IF(ISBLANK(E15),"UNKNOWN",E15) -> Standard Class | W15: =IF(ISBLANK(H15),"UNKNOWN",H15) -> Consumer | X15: =CONCATENATE(J15," - ",K15) -> Seattle - Washington | Y15: =IF(ISBLANK(P15),"UNKNOWN",P15) -> Binders | Z15: =IF(ISBLANK(R15),ROUND(AVERAGEIF($O$2:$O$600,O15,$R$2:$R$29),0),R15) -> 407.976 | AA15: =IF(ISBLANK(R15),ROUND(AVERAGEIF($Y$2:$Y$600,Y15,$R$2:$R$29),0),R15) -> 407.976 | AB15: =AA15*S15 -> 1223.928 | AC15: =AB15*(1-T15) -> 979.1424 | AD15: CA | AE15: =MID(B15,4,4) -> 2016 | AF15: =RIGHT(B15,6) -> 161389
A16: 15 | B16: US-2015-118983 | C16: 42330 | D16: 42334 | F16: HP-14815 | G16: Harold Pawlan | H16: Home Office | I16: United States | J16: Fort Worth | K16: Texas | L16: 76106 | M16: Central | N16: OFF-AP-10002311 | O16: Office Supplies | P16: Appliances | Q16: Holmes Replacement Filter for HEPA Air Cleaner, Very Large Room, HEPA Filter | R16: 68.81 | S16: 5 | T16: 0.8 | U16: -123.858 | V16: =IF(ISBLANK(E16),"UNKNOWN",E16) -> UNKNOWN | W16: =IF(ISBLANK(H16),"UNKNOWN",H16) -> Home Office | X16: =CONCATENATE(J16," - ",K16) -> Fort Worth - Texas | Y16: =IF(ISBLANK(P16),"UNKNOWN",P16) -> Appliances | Z16: =IF(ISBLANK(R16),ROUND(AVERAGEIF($O$2:$O$600,O16,$R$2:$R$29),0),R16) -> 68.81 | AA16: =IF(ISBLANK(R16),ROUND(AVERAGEIF($Y$2:$Y$600,Y16,$R$2:$R$29),0),R16) -> 68.81 | AB16: =AA16*S16 -> 344.05 | AC16: =AB16*(1-T16) -> 68.81 | AD16: US | AE16: =MID(B16,4,4) -> 2015 | AF16: =RIGHT(B16,6) -> 118983
A17: 16 | B17: US-2015-118983 | C17: 42330 | D17: 42334 | E17: Standard Class | F17: HP-14815 | G17: Harold Pawlan | H17: Home Office | I17: United States | J17: Fort Worth | K17: Texas | L17: 76106 | M17: Central | N17: OFF-BI-10000756 | O17: Office Supplies | P17: Binders | Q17: Storex DuraTech Recycled Plastic Frosted Binders | R17: 2.544 | S17: 3 | T17: 0.8 | U17: -3.816 | V17: =IF(ISBLANK(E17),"UNKNOWN",E17) -> Standard Class | W17: =IF(ISBLANK(H17),"UNKNOWN",H17) -> Home Office | X17: =CONCATENATE(J17," - ",K17) -> Fort Worth - Texas | Y17: =IF(ISBLANK(P17),"UNKNOWN",P17) -> Binders | Z17: =IF(ISBLANK(R17),ROUND(AVERAGEIF($O$2:$O$600,O17,$R$2:$R$29),0),R17) -> 2.544 | AA17: =IF(ISBLANK(R17),ROUND(AVERAGEIF($Y$2:$Y$600,Y17,$R$2:$R$29),0),R17) -> 2.544 | AB17: =AA17*S17 -> 7.632 | AC17: =AB17*(1-T17) -> 1.5264 | AD17: US | AE17: =MID(B17,4,4) -> 2015 | AF17: =RIGHT(B17,6) -> 118983
A18: 17 | B18: CA-2014-105893 | C18: 41954 | D18: 41961 | E18: Standard Class | F18: PK-19075 | G18: Pete Kriz | H18: Consumer | I18: United States | J18: Madison | K18: Wisconsin | L18: 53711 | M18: Central | N18: OFF-ST-10004186 | O18: Office Supplies | P18: Storage | Q18: Stur-D-Stor Shelving, Vertical 5-Shelf: 72"H x 36"W x 18 1/2"D | R18: 665.88 | S18: 6 | T18: 0 | U18: 13.3176 | V18: =IF(ISBLANK(E18),"UNKNOWN",E18) -> Standard Class | W18: =IF(ISBLANK(H18),"UNKNOWN",H18) -> Consumer | X18: =CONCATENATE(J18," - ",K18) -> Madison - Wisconsin | Y18: =IF(ISBLANK(P18),"UNKNOWN",P18) -> Storage | Z18: =IF(ISBLANK(R18),ROUND(AVERAGEIF($O$2:$O$600,O18,$R$2:$R$29),0),R18) -> 665.88 | AA18: =IF(ISBLANK(R18),ROUND(AVERAGEIF($Y$2:$Y$600,Y18,$R$2:$R$29),0),R18) -> 665.88 | AB18: =AA18*S18 -> 3995.28 | AC18: =AB18*(1-T18) -> 3995.28 | AD18: CA | AE18: =MID(B18,4,4) -> 2014 | AF18: =RIGHT(B18,6) -> 105893
A19: 18 | B19: CA-2014-167164 | C19: 41772 | D19: 41774 | E19: Second Class | F19: AG-10270 | G19: Alejandro Grove | H19: Consumer | I19: United States | J19: West Jordan | K19: Utah | L19: 84084 | M19: West | N19: OFF-ST-10000107 | O19: Office Supplies | P19: Storage | Q19: Fellowes Super Stor/Drawer | R19: 55.5 | S19: 2 | T19: 0 | U19: 9.99 | V19: =IF(ISBLANK(E19),"UNKNOWN",E19) -> Second Class | W19: =IF(ISBLANK(H19),"UNKNOWN",H19) -> Consumer | X19: =CONCATENATE(J19," - ",K19) -> West Jordan - Utah | Y19: =IF(ISBLANK(P19),"UNKNOWN",P19) -> Storage | Z19: =IF(ISBLANK(R19),ROUND(AVERAGEIF($O$2:$O$600,O19,$R$2:$R$29),0),R19) -> 55.5 | AA19: =IF(ISBLANK(R19),ROUND(AVERAGEIF($Y$2:$Y$600,Y19,$R$2:$R$29),0),R19) -> 55.5 | AB19: =AA19*S19 -> 111 | AC19: =AB19*(1-T19) -> 111 | AD19: CA | AE19: =MID(B19,4,4) -> 2014 | AF19: =RIGHT(B19,6) -> 167164
A20: 19 | B20: CA-2014-143336 | C20: 41878 | D20: 41883 | E20: Second Class | F20: ZD-21925 | G20: Zuschuss Donatelli | H20: Consumer | I20: United States | J20: San Francisco | K20: California | L20: 94109 | M20: West | N20: OFF-AR-10003056 | O20: Office Supplies | P20: Art | Q20: Newell 341 | R20: 8.56 | S20: 2 | T20: 0 | U20: 2.4824 | V20: =IF(ISBLANK(E20),"UNKNOWN",E20) -> Second Class | W20: =IF(ISBLANK(H20),"UNKNOWN",H20) -> Consumer | X20: =CONCATENATE(J20," - ",K20) -> San Francisco - California | Y20: =IF(ISBLANK(P20),"UNKNOWN",P20) -> Art | Z20: =IF(ISBLANK(R20),ROUND(AVERAGEIF($O$2:$O$600,O20,$R$2:$R$29),0),R20) -> 8.56 | AA20: =IF(ISBLANK(R20),ROUND(AVERAGEIF($Y$2:$Y$600,Y20,$R$2:$R$29),0),R20) -> 8.56 | AB20: =AA20*S20 -> 17.12 | AC20: =AB20*(1-T20) -> 17.12 | AD20: CA | AE20: =MID(B20,4,4) -> 2014 | AF20: =RIGHT(B20,6) -> 143336
A21: 20 | B21: CA-2014-143336 | C21: 41878 | D21: 41883 | E21: Second Class | F21: ZD-21925 | G21: Zuschuss Donatelli | H21: Consumer | I21: United States | J21: San Francisco | K21: California | L21: 94109 | M21: West | N21: TEC-PH-10001949 | O21: Technology | P21: Phones | Q21: Cisco SPA 501G IP Phone | R21: 213.48 | S21: 3 | T21: 0.2 | U21: 16.011 | V21: =IF(ISBLANK(E21),"UNKNOWN",E21) -> Second Class | W21: =IF(ISBLANK(H21),"UNKNOWN",H21) -> Consumer | X21: =CONCATENATE(J21," - ",K21) -> San Francisco - California | Y21: =IF(ISBLANK(P21),"UNKNOWN",P21) -> Phones | Z21: =IF(ISBLANK(R21),ROUND(AVERAGEIF($O$2:$O$600,O21,$R$2:$R$29),0),R21) -> 213.48 | AA21: =IF(ISBLANK(R21),ROUND(AVERAGEIF($Y$2:$Y$600,Y21,$R$2:$R$29),0),R21) -> 213.48 | AB21: =AA21*S21 -> 640.44 | AC21: =AB21*(1-T21) -> 512.352 | AD21: CA | AE21: =MID(B21,4,4) -> 2014 | AF21: =RIGHT(B21,6) -> 143336
A22: 21 | B22: CA-2014-143336 | C22: 41878 | D22: 41883 | E22: Second Class | F22: ZD-21925 | G22: Zuschuss Donatelli | H22: Consumer | I22: United States | J22: San Francisco | K22: California | L22: 94109 | M22: West | N22: OFF-BI-10002215 | O22: Office Supplies | Q22: Wilson Jones Hanging View Binder, White, 1" | R22: 22.72 | S22: 4 | T22: 0.2 | U22: 7.384 | V22: =IF(ISBLANK(E22),"UNKNOWN",E22) -> Second Class | W22: =IF(ISBLANK(H22),"UNKNOWN",H22) -> Consumer | X22: =CONCATENATE(J22," - ",K22) -> San Francisco - California | Y22: =IF(ISBLANK(P22),"UNKNOWN",P22) -> UNKNOWN | Z22: =IF(ISBLANK(R22),ROUND(AVERAGEIF($O$2:$O$600,O22,$R$2:$R$29),0),R22) -> 22.72 | AA22: =IF(ISBLANK(R22),ROUND(AVERAGEIF($Y$2:$Y$600,Y22,$R$2:$R$29),0),R22) -> 22.72 | AB22: =AA22*S22 -> 90.88 | AC22: =AB22*(1-T22) -> 72.704 | AD22: CA | AE22: =MID(B22,4,4) -> 2014 | AF22: =RIGHT(B22,6) -> 143336
A23: 22 | B23: CA-2016-137330 | C23: 42713 | D23: 42717 | E23: Standard Class | F23: KB-16585 | G23: Ken Black | H23: Corporate | I23: United States | J23: Fremont | K23: Nebraska | L23: 68025 | M23: Central | N23: OFF-AR-10000246 | O23: Office Supplies | P23: Art | Q23: Newell 318 | R23: 19.46 | S23: 7 | T23: 0 | U23: 5.0596 | V23: =IF(ISBLANK(E23),"UNKNOWN",E23) -> Standard Class | W23: =IF(ISBLANK(H23),"UNKNOWN",H23) -> Corporate | X23: =CONCATENATE(J23," - ",K23) -> Fremont - Nebraska | Y23: =IF(ISBLANK(P23),"UNKNOWN",P23) -> Art | Z23: =IF(ISBLANK(R23),ROUND(AVERAGEIF($O$2:$O$600,O23,$R$2:$R$29),0),R23) -> 19.46 | AA23: =IF(ISBLANK(R23),ROUND(AVERAGEIF($Y$2:$Y$600,Y23,$R$2:$R$29),0),R23) -> 19.46 | AB23: =AA23*S23 -> 136.22 | AC23: =AB23*(1-T23) -> 136.22 | AD23: CA | AE23: =MID(B23,4,4) -> 2016 | AF23: =RIGHT(B23,6) -> 137330
A24: 23 | B24: CA-2016-137330 | C24: 42713 | D24: 42717 | E24: Standard Class | F24: KB-16585 | G24: Ken Black | H24: Corporate | I24: United States | J24: Fremont | K24: Nebraska | L24: 68025 | M24: Central | N24: OFF-AP-10001492 | O24: Office Supplies | P24: Appliances | Q24: Acco Six-Outlet Power Strip, 4' Cord Length | R24: 60.34 | S24: 7 | T24: 0 | U24: 15.6884 | V24: =IF(ISBLANK(E24),"UNKNOWN",E24) -> Standard Class | W24: =IF(ISBLANK(H24),"UNKNOWN",H24) -> Corporate | X24: =CONCATENATE(J24," - ",K24) -> Fremont - Nebraska | Y24: =IF(ISBLANK(P24),"UNKNOWN",P24) -> Appliances | Z24: =IF(ISBLANK(R24),ROUND(AVERAGEIF($O$2:$O$600,O24,$R$2:$R$29),0),R24) -> 60.34 | AA24: =IF(ISBLANK(R24),ROUND(AVERAGEIF($Y$2:$Y$600,Y24,$R$2:$R$29),0),R24) -> 60.34 | AB24: =AA24*S24 -> 422.38 | AC24: =AB24*(1-T24) -> 422.38 | AD24: CA | AE24: =MID(B24,4,4) -> 2016 | AF24: =RIGHT(B24,6) -> 137330
A25: 24 | B25: US-2017-156909 | C25: 42932 | D25: 42934 | E25: Second Class | F25: SF-20065 | G25: Sandra Flanagan | H25: Consumer | I25: United States | J25: Philadelphia | K25: Pennsylvania | L25: 19140 | M25: East | N25: FUR-CH-10002774 | O25: Furniture | P25: Chairs | Q25: Global Deluxe Stacking Chair, Gray | R25: 71.372 | S25: 2 | T25: 0.3 | U25: -1.0196 | V25: =IF(ISBLANK(E25),"UNKNOWN",E25) -> Second Class | W25: =IF(ISBLANK(H25),"UNKNOWN",H25) -> Consumer | X25: =CONCATENATE(J25," - ",K25) -> Philadelphia - Pennsylvania | Y25: =IF(ISBLANK(P25),"UNKNOWN",P25) -> Chairs | Z25: =IF(ISBLANK(R25),ROUND(AVERAGEIF($O$2:$O$600,O25,$R$2:$R$29),0),R25) -> 71.372 | AA25: =IF(ISBLANK(R25),ROUND(AVERAGEIF($Y$2:$Y$600,Y25,$R$2:$R$29),0),R25) -> 71.372 | AB25: =AA25*S25 -> 142.744 | AC25: =AB25*(1-T25) -> 99.9208 | AD25: US | AE25: =MID(B25,4,4) -> 2017 | AF25: =RIGHT(B25,6) -> 156909
A26: 25 | B26: CA-2015-106320 | C26: 42272 | D26: 42277 | E26: Standard Class | F26: EB-13870 | G26: Emily Burns | H26: Consumer | I26: United States | J26: Orem | K26: Utah | L26: 84057 | M26: West | N26: FUR-TA-10000577 | O26: Furniture | P26: Tables | Q26: Bretford CR4500 Series Slim Rectangular Table | R26: 1044.63 | S26: 3 | T26: 0 | U26: 240.2649 | V26: =IF(ISBLANK(E26),"UNKNOWN",E26) -> Standard Class | W26: =IF(ISBLANK(H26),"UNKNOWN",H26) -> Consumer | X26: =CONCATENATE(J26," - ",K26) -> Orem - Utah | Y26: =IF(ISBLANK(P26),"UNKNOWN",P26) -> Tables | Z26: =IF(ISBLANK(R26),ROUND(AVERAGEIF($O$2:$O$600,O26,$R$2:$R$29),0),R26) -> 1044.63 | AA26: =IF(ISBLANK(R26),ROUND(AVERAGEIF($Y$2:$Y$600,Y26,$R$2:$R$29),0),R26) -> 1044.63 | AB26: =AA26*S26 -> 3133.89 | AC26: =AB26*(1-T26) -> 3133.89 | AD26: CA | AE26: =MID(B26,4,4) -> 2015 | AF26: =RIGHT(B26,6) -> 106320
A27: 26 | B27: CA-2016-121755 | C27: 42385 | D27: 42389 | E27: Second Class | F27: EH-13945 | G27: Eric Hoffmann | H27: Consumer | I27: United States | J27: Los Angeles | K27: California | L27: 90049 | M27: West | N27: OFF-BI-10001634 | O27: Office Supplies | P27: Binders | Q27: Wilson Jones Active Use Binders | R27: 11.648 | S27: 2 | T27: 0.2 | U27: 4.2224 | V27: =IF(ISBLANK(E27),"UNKNOWN",E27) -> Second Class | W27: =IF(ISBLANK(H27),"UNKNOWN",H27) -> Consumer | X27: =CONCATENATE(J27," - ",K27) -> Los Angeles - California | Y27: =IF(ISBLANK(P27),"UNKNOWN",P27) -> Binders | Z27: =IF(ISBLANK(R27),ROUND(AVERAGEIF($O$2:$O$600,O27,$R$2:$R$29),0),R27) -> 11.648 | AA27: =IF(ISBLANK(R27),ROUND(AVERAGEIF($Y$2:$Y$600,Y27,$R$2:$R$29),0),R27) -> 11.648 | AB27: =AA27*S27 -> 23.296 | AC27: =AB27*(1-T27) -> 18.6368 | AD27: CA | AE27: =MID(B27,4,4) -> 2016 | AF27: =RIGHT(B27,6) -> 121755
A28: 27 | B28: CA-2016-121755 | C28: 42385 | D28: 42389 | E28: Second Class | F28: EH-13945 | G28: Eric Hoffmann | H28: Consumer | I28: United States | J28: Los Angeles | K28: California | L28: 90049 | M28: West | N28: TEC-AC-10003027 | O28: Technology | P28: Accessories | Q28: Imation 8GB Mini TravelDrive USB 2.0 Flash Drive | R28: 90.57 | S28: 3 | T28: 0 | U28: 11.7741 | V28: =IF(ISBLANK(E28),"UNKNOWN",E28) -> Second Class | W28: =IF(ISBLANK(H28),"UNKNOWN",H28) -> Consumer | X28: =CONCATENATE(J28," - ",K28) -> Los Angeles - California | Y28: =IF(ISBLANK(P28),"UNKNOWN",P28) -> Accessories | Z28: =IF(ISBLANK(R28),ROUND(AVERAGEIF($O$2:$O$600,O28,$R$2:$R$29),0),R28) -> 90.57 | AA28: =IF(ISBLANK(R28),ROUND(AVERAGEIF($Y$2:$Y$600,Y28,$R$2:$R$29),0),R28) -> 90.57 | AB28: =AA28*S28 -> 271.71 | AC28: =AB28*(1-T28) -> 271.71 | AD28: CA | AE28: =MID(B28,4,4) -> 2016 | AF28: =RIGHT(B28,6) -> 121755
A29: 28 | B29: US-2015-150630 | C29: 42264 | D29: 42268 | E29: Standard Class | F29: TB-21520 | G29: Tracy Blumstein | H29: Consumer | I29: United States | J29: Philadelphia | K29: Pennsylvania | L29: 19140 | M29: East | N29: FUR-BO-10004834 | O29: Furniture | P29: Bookcases | Q29: Riverside Palais Royal Lawyers Bookcase, Royale Cherry Finish | R29: 3083.43 | S29: 7 | T29: 0.5 | U29: -1665.0522 | V29: =IF(ISBLANK(E29),"UNKNOWN",E29) -> Standard Class | W29: =IF(ISBLANK(H29),"UNKNOWN",H29) -> Consumer | X29: =CONCATENATE(J29," - ",K29) -> Philadelphia - Pennsylvania | Y29: =IF(ISBLANK(P29),"UNKNOWN",P29) -> Bookcases | Z29: =IF(ISBLANK(R29),ROUND(AVERAGEIF($O$2:$O$600,O29,$R$2:$R$29),0),R29) -> 3083.43 | AA29: =IF(ISBLANK(R29),ROUND(AVERAGEIF($Y$2:$Y$600,Y29,$R$2:$R$29),0),R29) -> 3083.43 | AB29: =AA29*S29 -> 21584.01 | AC29: =AB29*(1-T29) -> 10792.005 | AD29: US | AE29: =MID(B29,4,4) -> 2015 | AF29: =RIGHT(B29,6) -> 150630
A30: 29 | B30: US-2015-150630 | C30: 42264 | D30: 42268 | E30: Standard Class | F30: TB-21520 | G30: Tracy Blumstein | H30: Consumer | I30: United States | J30: Philadelphia | K30: Pennsylvania | L30: 19140 | M30: East | N30: OFF-BI-10000474 | O30: Office Supplies | P30: Binders | Q30: Avery Recycled Flexi-View Covers for Binding Systems | S30: 2 | T30: 0.7 | U30: -7.0532 | V30: =IF(ISBLANK(E30),"UNKNOWN",E30) -> Standard Class | W30: =IF(ISBLANK(H30),"UNKNOWN",H30) -> Consumer | X30: =CONCATENATE(J30," - ",K30) -> Philadelphia - Pennsylvania | Y30: =IF(ISBLANK(P30),"UNKNOWN",P30) -> Binders | Z30: =IF(ISBLANK(R30),ROUND(AVERAGEIF($O$2:$O$600,O30,$R$2:$R$29),0),R30) -> 124 | AA30: =IF(ISBLANK(R30),ROUND(AVERAGEIF($Y$2:$Y$600,Y30,$R$2:$R$29),0),R30) -> 190 | AB30: =AA30*S30 -> 380 | AC30: =AB30*(1-T30) -> 114 | AD30: US | AE30: =MID(B30,4,4) -> 2015 | AF30: =RIGHT(B30,6) -> 150630
A31: 30 | B31: US-2015-150630 | C31: 42264 | D31: 42268 | E31: Standard Class | F31: TB-21520 | G31: Tracy Blumstein | H31: Consumer | I31: United States | J31: Philadelphia | K31: Pennsylvania | L31: 19140 | M31: East | N31: FUR-FU-10004848 | O31: Furniture | P31: Furnishings | Q31: Howard Miller 13-3/4" Diameter Brushed Chrome Round Wall Clock | R31: 124.2 | S31: 3 | T31: 0.2 | U31: 15.525 | V31: =IF(ISBLANK(E31),"UNKNOWN",E31) -> Standard Class | W31: =IF(ISBLANK(H31),"UNKNOWN",H31) -> Consumer | X31: =CONCATENATE(J31," - ",K31) -> Philadelphia - Pennsylvania | Y31: =IF(ISBLANK(P31),"UNKNOWN",P31) -> Furnishings | Z31: =IF(ISBLANK(R31),ROUND(AVERAGEIF($O$2:$O$600,O31,$R$2:$R$29),0),R31) -> 124.2 | AA31: =IF(ISBLANK(R31),ROUND(AVERAGEIF($Y$2:$Y$600,Y31,$R$2:$R$29),0),R31) -> 124.2 | AB31: =AA31*S31 -> 372.6 | AC31: =AB31*(1-T31) -> 298.08 | AD31: US | AE31: =MID(B31,4,4) -> 2015 | AF31: =RIGHT(B31,6) -> 150630
A32: 31 | B32: US-2015-150630 | C32: 42264 | D32: 42268 | E32: Standard Class | F32: TB-21520 | G32: Tracy Blumstein | H32: Consumer | I32: United States | J32: Philadelphia | K32: Pennsylvania | L32: 19140 | M32: East | N32: OFF-EN-10001509 | O32: Office Supplies | P32: Envelopes | Q32: Poly String Tie Envelopes | R32: 3.264 | S32: 2 | T32: 0.2 | U32: 1.1016 | V32: =IF(ISBLANK(E32),"UNKNOWN",E32) -> Standard Class | W32: =IF(ISBLANK(H32),"UNKNOWN",H32) -> Consumer | X32: =CONCATENATE(J32," - ",K32) -> Philadelphia - Pennsylvania | Y32: =IF(ISBLANK(P32),"UNKNOWN",P32) -> Envelopes | Z32: =IF(ISBLANK(R32),ROUND(AVERAGEIF($O$2:$O$600,O32,$R$2:$R$29),0),R32) -> 3.264 | AA32: =IF(ISBLANK(R32),ROUND(AVERAGEIF($Y$2:$Y$600,Y32,$R$2:$R$29),0),R32) -> 3.264 | AB32: =AA32*S32 -> 6.528 | AC32: =AB32*(1-T32) -> 5.2224 | AD32: US | AE32: =MID(B32,4,4) -> 2015 | AF32: =RIGHT(B32,6) -> 150630
A33: 32 | B33: US-2015-150630 | C33: 42264 | D33: 42268 | E33: Standard Class | F33: TB-21520 | G33: Tracy Blumstein | H33: Consumer | I33: United States | J33: Philadelphia | K33: Pennsylvania | L33: 19140 | M33: East | N33: OFF-AR-10004042 | O33: Office Supplies | P33: Art | Q33: BOSTON Model 1800 Electric Pencil Sharpeners, Putty/Woodgrain | R33: 86.304 | S33: 6 | T33: 0.2 | U33: 9.7092 | V33: =IF(ISBLANK(E33),"UNKNOWN",E33) -> Standard Class | W33: =IF(ISBLANK(H33),"UNKNOWN",H33) -> Consumer | X33: =CONCATENATE(J33," - ",K33) -> Philadelphia - Pennsylvania | Y33: =IF(ISBLANK(P33),"UNKNOWN",P33) -> Art | Z33: =IF(ISBLANK(R33),ROUND(AVERAGEIF($O$2:$O$600,O33,$R$2:$R$29),0),R33) -> 86.304 | AA33: =IF(ISBLANK(R33),ROUND(AVERAGEIF($Y$2:$Y$600,Y33,$R$2:$R$29),0),R33) -> 86.304 | AB33: =AA33*S33 -> 517.824 | AC33: =AB33*(1-T33) -> 414.2592 | AD33: US | AE33: =MID(B33,4,4) -> 2015 | AF33: =RIGHT(B33,6) -> 150630
A34: 33 | B34: US-2015-150630 | C34: 42264 | D34: 42268 | E34: Standard Class | F34: TB-21520 | G34: Tracy Blumstein | H34: Consumer | I34: United States | J34: Philadelphia | K34: Pennsylvania | L34: 19140 | M34: East | N34: OFF-BI-10001525 | O34: Office Supplies | P34: Binders | Q34: Acco Pressboard Covers with Storage Hooks, 14 7/8" x 11", Executive Red | R34: 6.858 | S34: 6 | T34: 0.7 | U34: -5.715 | V34: =IF(ISBLANK(E34),"UNKNOWN",E34) -> Standard Class | W34: =IF(ISBLANK(H34),"UNKNOWN",H34) -> Consumer | X34: =CONCATENATE(J34," - ",K34) -> Philadelphia - Pennsylvania | Y34: =IF(ISBLANK(P34),"UNKNOWN",P34) -> Binders | Z34: =IF(ISBLANK(R34),ROUND(AVERAGEIF($O$2:$O$600,O34,$R$2:$R$29),0),R34) -> 6.858 | AA34: =IF(ISBLANK(R34),ROUND(AVERAGEIF($Y$2:$Y$600,Y34,$R$2:$R$29),0),R34) -> 6.858 | AB34: =AA34*S34 -> 41.148 | AC34: =AB34*(1-T34) -> 12.3444 | AD34: US | AE34: =MID(B34,4,4) -> 2015 | AF34: =RIGHT(B34,6) -> 150630
A35: 34 | B35: US-2015-150630 | C35: 42264 | D35: 42268 | E35: Standard Class | F35: TB-21520 | G35: Tracy Blumstein | H35: Consumer | I35: United States | J35: Philadelphia | K35: Pennsylvania | L35: 19140 | M35: East | N35: OFF-AR-10001683 | O35: Office Supplies | P35: Art | Q35: Lumber Crayons | R35: 15.76 | S35: 2 | T35: 0.2 | U35: 3.546 | V35: =IF(ISBLANK(E35),"UNKNOWN",E35) -> Standard Class | W35: =IF(ISBLANK(H35),"UNKNOWN",H35) -> Consumer | X35: =CONCATENATE(J35," - ",K35) -> Philadelphia - Pennsylvania | Y35: =IF(ISBLANK(P35),"UNKNOWN",P35) -> Art | Z35: =IF(ISBLANK(R35),ROUND(AVERAGEIF($O$2:$O$600,O35,$R$2:$R$29),0),R35) -> 15.76 | AA35: =IF(ISBLANK(R35),ROUND(AVERAGEIF($Y$2:$Y$600,Y35,$R$2:$R$29),0),R35) -> 15.76 | AB35: =AA35*S35 -> 31.52 | AC35: =AB35*(1-T35) -> 25.216 | AD35: US | AE35: =MID(B35,4,4) -> 2015 | AF35: =RIGHT(B35,6) -> 150630
A36: 35 | B36: CA-2017-107727 | C36: 43027 | D36: 43031 | E36: Second Class | F36: MA-17560 | G36: Matt Abelman | H36: Home Office | I36: United States | J36: Houston | K36: Texas | L36: 77095 | M36: Central | N36: OFF-PA-10000249 | O36: Office Supplies | P36: Paper | Q36: Easy-staple paper | R36: 29.472 | S36: 3 | T36: 0.2 | U36: 9.9468 | V36: =IF(ISBLANK(E36),"UNKNOWN",E36) -> Second Class | W36: =IF(ISBLANK(H36),"UNKNOWN",H36) -> Home Office | X36: =CONCATENATE(J36," - ",K36) -> Houston - Texas | Y36: =IF(ISBLANK(P36),"UNKNOWN",P36) -> Paper | Z36: =IF(ISBLANK(R36),ROUND(AVERAGEIF($O$2:$O$600,O36,$R$2:$R$29),0),R36) -> 29.472 | AA36: =IF(ISBLANK(R36),ROUND(AVERAGEIF($Y$2:$Y$600,Y36,$R$2:$R$29),0),R36) -> 29.472 | AB36: =AA36*S36 -> 88.416 | AC36: =AB36*(1-T36) -> 70.7328 | AD36: CA | AE36: =MID(B36,4,4) -> 2017 | AF36: =RIGHT(B36,6) -> 107727
A37: 36 | B37: CA-2016-117590 | C37: 42712 | D37: 42714 | E37: First Class | F37: GH-14485 | G37: Gene Hale | H37: Corporate | I37: United States | J37: Richardson | K37: Texas | L37: 75080 | M37: Central | N37: TEC-PH-10004977 | O37: Technology | P37: Phones | Q37: GE 30524EE4 | R37: 1097.544 | S37: 7 | T37: 0.2 | U37: 123.4737 | V37: =IF(ISBLANK(E37),"UNKNOWN",E37) -> First Class | W37: =IF(ISBLANK(H37),"UNKNOWN",H37) -> Corporate | X37: =CONCATENATE(J37," - ",K37) -> Richardson - Texas | Y37: =IF(ISBLANK(P37),"UNKNOWN",P37) -> Phones | Z37: =IF(ISBLANK(R37),ROUND(AVERAGEIF($O$2:$O$600,O37,$R$2:$R$29),0),R37) -> 1097.544 | AA37: =IF(ISBLANK(R37),ROUND(AVERAGEIF($Y$2:$Y$600,Y37,$R$2:$R$29),0),R37) -> 1097.544 | AB37: =AA37*S37 -> 7682.808 | AC37: =AB37*(1-T37) -> 6146.2464 | AD37: CA | AE37: =MID(B37,4,4) -> 2016 | AF37: =RIGHT(B37,6) -> 117590
A38: 37 | B38: CA-2016-117590 | C38: 42712 | D38: 42714 | E38: First Class | F38: GH-14485 | G38: Gene Hale | H38: Corporate | I38: United States | J38: Richardson | K38: Texas | L38: 75080 | M38: Central | N38: FUR-FU-10003664 | O38: Furniture | P38: Furnishings | Q38: Electrix Architect's Clamp-On Swing Arm Lamp, Black | R38: 190.92 | S38: 5 | T38: 0.6 | U38: -147.963 | V38: =IF(ISBLANK(E38),"UNKNOWN",E38) -> First Class | W38: =IF(ISBLANK(H38),"UNKNOWN",H38) -> Corporate | X38: =CONCATENATE(J38," - ",K38) -> Richardson - Texas | Y38: =IF(ISBLANK(P38),"UNKNOWN",P38) -> Furnishings | Z38: =IF(ISBLANK(R38),ROUND(AVERAGEIF($O$2:$O$600,O38,$R$2:$R$29),0),R38) -> 190.92 | AA38: =IF(ISBLANK(R38),ROUND(AVERAGEIF($Y$2:$Y$600,Y38,$R$2:$R$29),0),R38) -> 190.92 | AB38: =AA38*S38 -> 954.6 | AC38: =AB38*(1-T38) -> 381.84 | AD38: CA | AE38: =MID(B38,4,4) -> 2016 | AF38: =RIGHT(B38,6) -> 117590
A39: 38 | B39: CA-2015-117415 | C39: 42365 | D39: 42369 | E39: Standard Class | F39: SN-20710 | G39: Steve Nguyen | H39: Home Office | I39: United States | J39: Houston | K39: Texas | L39: 77041 | M39: Central | N39: OFF-EN-10002986 | O39: Office Supplies | P39: Envelopes | Q39: #10-4 1/8" x 9 1/2" Premium Diagonal Seam Envelopes | R39: 113.328 | S39: 9 | T39: 0.2 | U39: 35.415 | V39: =IF(ISBLANK(E39),"UNKNOWN",E39) -> Standard Class | W39: =IF(ISBLANK(H39),"UNKNOWN",H39) -> Home Office | X39: =CONCATENATE(J39," - ",K39) -> Houston - Texas | Y39: =IF(ISBLANK(P39),"UNKNOWN",P39) -> Envelopes | Z39: =IF(ISBLANK(R39),ROUND(AVERAGEIF($O$2:$O$600,O39,$R$2:$R$29),0),R39) -> 113.328 | AA39: =IF(ISBLANK(R39),ROUND(AVERAGEIF($Y$2:$Y$600,Y39,$R$2:$R$29),0),R39) -> 113.328 | AB39: =AA39*S39 -> 1019.952 | AC39: =AB39*(1-T39) -> 815.9616 | AD39: CA | AE39: =MID(B39,4,4) -> 2015 | AF39: =RIGHT(B39,6) -> 117415
A40: 39 | B40: CA-2015-117415 | C40: 42365 | D40: 42369 | E40: Standard Class | F40: SN-20710 | G40: Steve Nguyen | H40: Home Office | I40: United States | J40: Houston | K40: Texas | L40: 77041 | M40: Central | N40: FUR-BO-10002545 | O40: Furniture | P40: Bookcases | Q40: Atlantic Metals Mobile 3-Shelf Bookcases, Custom Colors | R40: 532.3992 | S40: 3 | T40: 0.32 | U40: -46.9764 | V40: =IF(ISBLANK(E40),"UNKNOWN",E40) -> Standard Class | W40: =IF(ISBLANK(H40),"UNKNOWN",H40) -> Home Office | X40: =CONCATENATE(J40," - ",K40) -> Houston - Texas | Y40: =IF(ISBLANK(P40),"UNKNOWN",P40) -> Bookcases | Z40: =IF(ISBLANK(R40),ROUND(AVERAGEIF($O$2:$O$600,O40,$R$2:$R$29),0),R40) -> 532.3992 | AA40: =IF(ISBLANK(R40),ROUND(AVERAGEIF($Y$2:$Y$600,Y40,$R$2:$R$29),0),R40) -> 532.3992 | AB40: =AA40*S40 -> 1597.1976 | AC40: =AB40*(1-T40) -> 1086.0944 | AD40: CA | AE40: =MID(B40,4,4) -> 2015 | AF40: =RIGHT(B40,6) -> 117415
A41: 40 | B41: CA-2015-117415 | C41: 42365 | D41: 42369 | E41: Standard Class | F41: SN-20710 | G41: Steve Nguyen | I41: United States | J41: Houston | K41: Texas | L41: 77041 | M41: Central | N41: FUR-CH-10004218 | O41: Furniture | P41: Chairs | Q41: Global Fabric Manager's Chair, Dark Gray | R41: 212.058 | S41: 3 | T41: 0.3 | U41: -15.147 | V41: =IF(ISBLANK(E41),"UNKNOWN",E41) -> Standard Class | W41: =IF(ISBLANK(H41),"UNKNOWN",H41) -> UNKNOWN | X41: =CONCATENATE(J41," - ",K41) -> Houston - Texas | Y41: =IF(ISBLANK(P41),"UNKNOWN",P41) -> Chairs | Z41: =IF(ISBLANK(R41),ROUND(AVERAGEIF($O$2:$O$600,O41,$R$2:$R$29),0),R41) -> 212.058 | AA41: =IF(ISBLANK(R41),ROUND(AVERAGEIF($Y$2:$Y$600,Y41,$R$2:$R$29),0),R41) -> 212.058 | AB41: =AA41*S41 -> 636.174 | AC41: =AB41*(1-T41) -> 445.3218 | AD41: CA | AE41: =MID(B41,4,4) -> 2015 | AF41: =RIGHT(B41,6) -> 117415
A42: 41 | B42: CA-2015-117415 | C42: 42365 | D42: 42369 | E42: Standard Class | F42: SN-20710 | G42: Steve Nguyen | H42: Home Office | I42: United States | J42: Houston | K42: Texas | L42: 77041 | M42: Central | N42: TEC-PH-10000486 | O42: Technology | P42: Phones | Q42: Plantronics HL10 Handset Lifter | R42: 371.168 | S42: 4 | T42: 0.2 | U42: 41.7564 | V42: =IF(ISBLANK(E42),"UNKNOWN",E42) -> Standard Class | W42: =IF(ISBLANK(H42),"UNKNOWN",H42) -> Home Office | X42: =CONCATENATE(J42," - ",K42) -> Houston - Texas | Y42: =IF(ISBLANK(P42),"UNKNOWN",P42) -> Phones | Z42: =IF(ISBLANK(R42),ROUND(AVERAGEIF($O$2:$O$600,O42,$R$2:$R$29),0),R42) -> 371.168 | AA42: =IF(ISBLANK(R42),ROUND(AVERAGEIF($Y$2:$Y$600,Y42,$R$2:$R$29),0),R42) -> 371.168 | AB42: =AA42*S42 -> 1484.672 | AC42: =AB42*(1-T42) -> 1187.7376 | AD42: CA | AE42: =MID(B42,4,4) -> 2015 | AF42: =RIGHT(B42,6) -> 117415
A43: 42 | B43: CA-2017-120999 | C43: 42988 | D43: 42993 | E43: Standard Class | F43: LC-16930 | G43: Linda Cazamias | H43: Corporate | I43: United States | J43: Naperville | K43: Illinois | L43: 60540 | M43: Central | N43: TEC-PH-10004093 | O43: Technology | P43: Phones | Q43: Panasonic Kx-TS550 | R43: 147.168 | S43: 4 | T43: 0.2 | U43: 16.5564 | V43: =IF(ISBLANK(E43),"UNKNOWN",E43) -> Standard Class | W43: =IF(ISBLANK(H43),"UNKNOWN",H43) -> Corporate | X43: =CONCATENATE(J43," - ",K43) -> Naperville - Illinois | Y43: =IF(ISBLANK(P43),"UNKNOWN",P43) -> Phones | Z43: =IF(ISBLANK(R43),ROUND(AVERAGEIF($O$2:$O$600,O43,$R$2:$R$29),0),R43) -> 147.168 | AA43: =IF(ISBLANK(R43),ROUND(AVERAGEIF($Y$2:$Y$600,Y43,$R$2:$R$29),0),R43) -> 147.168 | AB43: =AA43*S43 -> 588.672 | AC43: =AB43*(1-T43) -> 470.9376 | AD43: CA | AE43: =MID(B43,4,4) -> 2017 | AF43: =RIGHT(B43,6) -> 120999
A44: 43 | B44: CA-2016-101343 | C44: 42568 | D44: 42573 | E44: Standard Class | F44: RA-19885 | G44: Ruben Ausman | H44: Corporate | I44: United States | J44: Los Angeles | K44: California | L44: 90049 | M44: West | N44: OFF-ST-10003479 | O44: Office Supplies | P44: Storage | Q44: Eldon Base for stackable storage shelf, platinum | R44: 77.88 | S44: 2 | T44: 0 | U44: 3.894 | V44: =IF(ISBLANK(E44),"UNKNOWN",E44) -> Standard Class | W44: =IF(ISBLANK(H44),"UNKNOWN",H44) -> Corporate | X44: =CONCATENATE(J44," - ",K44) -> Los Angeles - California | Y44: =IF(ISBLANK(P44),"UNKNOWN",P44) -> Storage | Z44: =IF(ISBLANK(R44),ROUND(AVERAGEIF($O$2:$O$600,O44,$R$2:$R$29),0),R44) -> 77.88 | AA44: =IF(ISBLANK(R44),ROUND(AVERAGEIF($Y$2:$Y$600,Y44,$R$2:$R$29),0),R44) -> 77.88 | AB44: =AA44*S44 -> 155.76 | AC44: =AB44*(1-T44) -> 155.76 | AD44: CA | AE44: =MID(B44,4,4) -> 2016 | AF44: =RIGHT(B44,6) -> 101343
A45: 44 | B45: CA-2017-139619 | C45: 42997 | D45: 43001 | E45: Standard Class | F45: ES-14080 | G45: Erin Smith | H45: Corporate | I45: United States | J45: Melbourne | K45: Florida | L45: 32935 | M45: South | N45: OFF-ST-10003282 | O45: Office Supplies | P45: Storage | Q45: Advantus 10-Drawer Portable Organizer, Chrome Metal Frame, Smoke Drawers | R45: 95.616 | S45: 2 | T45: 0.2 | U45: 9.5616 | V45: =IF(ISBLANK(E45),"UNKNOWN",E45) -> Standard Class | W45: =IF(ISBLANK(H45),"UNKNOWN",H45) -> Corporate | X45: =CONCATENATE(J45," - ",K45) -> Melbourne - Florida | Y45: =IF(ISBLANK(P45),"UNKNOWN",P45) -> Storage | Z45: =IF(ISBLANK(R45),ROUND(AVERAGEIF($O$2:$O$600,O45,$R$2:$R$29),0),R45) -> 95.616 | AA45: =IF(ISBLANK(R45),ROUND(AVERAGEIF($Y$2:$Y$600,Y45,$R$2:$R$29),0),R45) -> 95.616 | AB45: =AA45*S45 -> 191.232 | AC45: =AB45*(1-T45) -> 152.9856 | AD45: CA | AE45: =MID(B45,4,4) -> 2017 | AF45: =RIGHT(B45,6) -> 139619
A46: 45 | B46: CA-2016-118255 | C46: 42440 | D46: 42442 | E46: First Class | F46: ON-18715 | G46: Odella Nelson | H46: Corporate | I46: United States | J46: Eagan | K46: Minnesota | L46: 55122 | M46: Central | N46: TEC-AC-10000171 | O46: Technology | P46: Accessories | Q46: Verbatim 25 GB 6x Blu-ray Single Layer Recordable Disc, 25/Pack | R46: 45.98 | S46: 2 | T46: 0 | U46: 19.7714 | V46: =IF(ISBLANK(E46),"UNKNOWN",E46) -> First Class | W46: =IF(ISBLANK(H46),"UNKNOWN",H46) -> Corporate | X46: =CONCATENATE(J46," - ",K46) -> Eagan - Minnesota | Y46: =IF(ISBLANK(P46),"UNKNOWN",P46) -> Accessories | Z46: =IF(ISBLANK(R46),ROUND(AVERAGEIF($O$2:$O$600,O46,$R$2:$R$29),0),R46) -> 45.98 | AA46: =IF(ISBLANK(R46),ROUND(AVERAGEIF($Y$2:$Y$600,Y46,$R$2:$R$29),0),R46) -> 45.98 | AB46: =AA46*S46 -> 91.96 | AC46: =AB46*(1-T46) -> 91.96 | AD46: CA | AE46: =MID(B46,4,4) -> 2016 | AF46: =RIGHT(B46,6) -> 118255
A47: 46 | B47: CA-2016-118255 | C47: 42440 | D47: 42442 | E47: First Class | F47: ON-18715 | G47: Odella Nelson | H47: Corporate | I47: United States | J47: Eagan | K47: Minnesota | L47: 55122 | M47: Central | N47: OFF-BI-10003291 | O47: Office Supplies | P47: Binders | Q47: Wilson Jones Leather-Like Binders with DublLock Round Rings | R47: 17.46 | S47: 2 | T47: 0 | U47: 8.2062 | V47: =IF(ISBLANK(E47),"UNKNOWN",E47) -> First Class | W47: =IF(ISBLANK(H47),"UNKNOWN",H47) -> Corporate | X47: =CONCATENATE(J47," - ",K47) -> Eagan - Minnesota | Y47: =IF(ISBLANK(P47),"UNKNOWN",P47) -> Binders | Z47: =IF(ISBLANK(R47),ROUND(AVERAGEIF($O$2:$O$600,O47,$R$2:$R$29),0),R47) -> 17.46 | AA47: =IF(ISBLANK(R47),ROUND(AVERAGEIF($Y$2:$Y$600,Y47,$R$2:$R$29),0),R47) -> 17.46 | AB47: =AA47*S47 -> 34.92 | AC47: =AB47*(1-T47) -> 34.92 | AD47: CA | AE47: =MID(B47,4,4) -> 2016 | AF47: =RIGHT(B47,6) -> 118255
A48: 47 | B48: CA-2014-146703 | C48: 41932 | D48: 41937 | E48: Second Class | F48: PO-18865 | G48: Patrick O'Donnell | H48: Consumer | I48: United States | J48: Westland | K48: Michigan | L48: 48185 | M48: Central | N48: OFF-ST-10001713 | O48: Office Supplies | P48: Storage | Q48: Gould Plastics 9-Pocket Panel Bin, 18-3/8w x 5-1/4d x 20-1/2h, Black | R48: 211.96 | S48: 4 | T48: 0 | U48: 8.4784 | V48: =IF(ISBLANK(E48),"UNKNOWN",E48) -> Second Class | W48: =IF(ISBLANK(H48),"UNKNOWN",H48) -> Consumer | X48: =CONCATENATE(J48," - ",K48) -> Westland - Michigan | Y48: =IF(ISBLANK(P48),"UNKNOWN",P48) -> Storage | Z48: =IF(ISBLANK(R48),ROUND(AVERAGEIF($O$2:$O$600,O48,$R$2:$R$29),0),R48) -> 211.96 | AA48: =IF(ISBLANK(R48),ROUND(AVERAGEIF($Y$2:$Y$600,Y48,$R$2:$R$29),0),R48) -> 211.96 | AB48: =AA48*S48 -> 847.84 | AC48: =AB48*(1-T48) -> 847.84 | AD48: CA | AE48: =MID(B48,4,4) -> 2014 | AF48: =RIGHT(B48,6) -> 146703
A49: 48 | B49: CA-2016-169194 | C49: 42541 | D49: 42546 | E49: Standard Class | F49: LH-16900 | G49: Lena Hernandez | H49: Consumer | I49: United States | J49: Dover | K49: Delaware | L49: 19901 | M49: East | N49: TEC-AC-10002167 | O49: Technology | P49: Accessories | Q49: Imation 8gb Micro Traveldrive Usb 2.0 Flash Drive | R49: 45 | S49: 3 | T49: 0 | U49: 4.95 | V49: =IF(ISBLANK(E49),"UNKNOWN",E49) -> Standard Class | W49: =IF(ISBLANK(H49),"UNKNOWN",H49) -> Consumer | X49: =CONCATENATE(J49," - ",K49) -> Dover - Delaware | Y49: =IF(ISBLANK(P49),"UNKNOWN",P49) -> Accessories | Z49: =IF(ISBLANK(R49),ROUND(AVERAGEIF($O$2:$O$600,O49,$R$2:$R$29),0),R49) -> 45 | AA49: =IF(ISBLANK(R49),ROUND(AVERAGEIF($Y$2:$Y$600,Y49,$R$2:$R$29),0),R49) -> 45 | AB49: =AA49*S49 -> 135 | AC49: =AB49*(1-T49) -> 135 | AD49: CA | AE49: =MID(B49,4,4) -> 2016 | AF49: =RIGHT(B49,6) -> 169194
A50: 49 | B50: CA-2016-169194 | C50: 42541 | D50: 42546 | E50: Standard Class | F50: LH-16900 | G50: Lena Hernandez | H50: Consumer | I50: United States | J50: Dover | K50: Delaware | L50: 19901 | M50: East | N50: TEC-PH-10003988 | O50: Technology | P50: Phones | Q50: LF Elite 3D Dazzle Designer Hard Case Cover, Lf Stylus Pen and Wiper For Apple Iphone 5c Mini Lite | R50: 21.8 | S50: 2 | T50: 0 | U50: 6.104 | V50: =IF(ISBLANK(E50),"UNKNOWN",E50) -> Standard Class | W50: =IF(ISBLANK(H50),"UNKNOWN",H50) -> Consumer | X50: =CONCATENATE(J50," - ",K50) -> Dover - Delaware | Y50: =IF(ISBLANK(P50),"UNKNOWN",P50) -> Phones | Z50: =IF(ISBLANK(R50),ROUND(AVERAGEIF($O$2:$O$600,O50,$R$2:$R$29),0),R50) -> 21.8 | AA50: =IF(ISBLANK(R50),ROUND(AVERAGEIF($Y$2:$Y$600,Y50,$R$2:$R$29),0),R50) -> 21.8 | AB50: =AA50*S50 -> 43.6 | AC50: =AB50*(1-T50) -> 43.6 | AD50: CA | AE50: =MID(B50,4,4) -> 2016 | AF50: =RIGHT(B50,6) -> 169194
A51: 50 | B51: CA-2015-115742 | C51: 42112 | D51: 42116 | E51: Standard Class | F51: DP-13000 | G51: Darren Powers | H51: Consumer | I51: United States | J51: New Albany | K51: Indiana | L51: 47150 | M51: Central | N51: OFF-BI-10004410 | O51: Office Supplies | P51: Binders | Q51: C-Line Peel & Stick Add-On Filing Pockets, 8-3/4 x 5-1/8, 10/Pack | R51: 38.22 | S51: 6 | T51: 0 | U51: 17.9634 | V51: =IF(ISBLANK(E51),"UNKNOWN",E51) -> Standard Class | W51: =IF(ISBLANK(H51),"UNKNOWN",H51) -> Consumer | X51: =CONCATENATE(J51," - ",K51) -> New Albany - Indiana | Y51: =IF(ISBLANK(P51),"UNKNOWN",P51) -> Binders | Z51: =IF(ISBLANK(R51),ROUND(AVERAGEIF($O$2:$O$600,O51,$R$2:$R$29),0),R51) -> 38.22 | AA51: =IF(ISBLANK(R51),ROUND(AVERAGEIF($Y$2:$Y$600,Y51,$R$2:$R$29),0),R51) -> 38.22 | AB51: =AA51*S51 -> 229.32 | AC51: =AB51*(1-T51) -> 229.32 | AD51: CA | AE51: =MID(B51,4,4) -> 2015 | AF51: =RIGHT(B51,6) -> 115742
A52: 51 | B52: CA-2015-115742 | C52: 42112 | D52: 42116 | E52: Standard Class | F52: DP-13000 | G52: Darren Powers | H52: Consumer | I52: United States | J52: New Albany | K52: Indiana | L52: 47150 | M52: Central | N52: OFF-LA-10002762 | O52: Office Supplies | P52: Labels | Q52: Avery 485 | R52: 75.18 | S52: 6 | T52: 0 | U52: 35.3346 | V52: =IF(ISBLANK(E52),"UNKNOWN",E52) -> Standard Class | W52: =IF(ISBLANK(H52),"UNKNOWN",H52) -> Consumer | X52: =CONCATENATE(J52," - ",K52) -> New Albany - Indiana | Y52: =IF(ISBLANK(P52),"UNKNOWN",P52) -> Labels | Z52: =IF(ISBLANK(R52),ROUND(AVERAGEIF($O$2:$O$600,O52,$R$2:$R$29),0),R52) -> 75.18 | AA52: =IF(ISBLANK(R52),ROUND(AVERAGEIF($Y$2:$Y$600,Y52,$R$2:$R$29),0),R52) -> 75.18 | AB52: =AA52*S52 -> 451.08 | AC52: =AB52*(1-T52) -> 451.08 | AD52: CA | AE52: =MID(B52,4,4) -> 2015 | AF52: =RIGHT(B52,6) -> 115742
A53: 52 | B53: CA-2015-115742 | C53: 42112 | D53: 42116 | E53: Standard Class | F53: DP-13000 | G53: Darren Powers | H53: Consumer | I53: United States | J53: New Albany | K53: Indiana | L53: 47150 | M53: Central | N53: FUR-FU-10001706 | O53: Furniture | P53: Furnishings | Q53: Longer-Life Soft White Bulbs | R53: 6.16 | S53: 2 | T53: 0 | U53: 2.9568 | V53: =IF(ISBLANK(E53),"UNKNOWN",E53) -> Standard Class | W53: =IF(ISBLANK(H53),"UNKNOWN",H53) -> Consumer | X53: =CONCATENATE(J53," - ",K53) -> New Albany - Indiana | Y53: =IF(ISBLANK(P53),"UNKNOWN",P53) -> Furnishings | Z53: =IF(ISBLANK(R53),ROUND(AVERAGEIF($O$2:$O$600,O53,$R$2:$R$29),0),R53) -> 6.16 | AA53: =IF(ISBLANK(R53),ROUND(AVERAGEIF($Y$2:$Y$600,Y53,$R$2:$R$29),0),R53) -> 6.16 | AB53: =AA53*S53 -> 12.32 | AC53: =AB53*(1-T53) -> 12.32 | AD53: CA | AE53: =MID(B53,4,4) -> 2015 | AF53: =RIGHT(B53,6) -> 115742
... A60: 59 | B60: CA-2016-111682 | C60: 42538 | D60: 42539 | E60: First Class | F60: TB-21055 | G60: Ted Butterfield | H60: Consumer | I60: United States | J60: Troy | K60: New York | L60: 12180 | M60: East | N60: OFF-PA-10000587 | O60: Office Supplies | P60: Paper | Q60: Array Parchment Paper, Assorted Colors | R60: 14.56 | S60: 2 | T60: 0 | U60: 6.9888 | V60: =IF(ISBLANK(E60),"UNKNOWN",E60) -> First Class | W60: =IF(ISBLANK(H60),"UNKNOWN",H60) -> Consumer | X60: =CONCATENATE(J60," - ",K60) -> Troy - New York | Y60: =IF(ISBLANK(P60),"UNKNOWN",P60) -> Paper | Z60: =IF(ISBLANK(R60),ROUND(AVERAGEIF($O$2:$O$600,O60,$R$2:$R$29),0),R60) -> 14.56 | AA60: =IF(ISBLANK(R60),ROUND(AVERAGEIF($Y$2:$Y$600,Y60,$R$2:$R$29),0),R60) -> 14.56 | AB60: =AA60*S60 -> 29.12 | AC60: =AB60*(1-T60) -> 29.12 | AD60: CA | AE60: =MID(B60,4,4) -> 2016 | AF60: =RIGHT(B60,6) -> 111682
A61: 60 | B61: CA-2016-111682 | C61: 42538 | D61: 42539 | E61: First Class | F61: TB-21055 | G61: Ted Butterfield | H61: Consumer | I61: United States | J61: Troy | K61: New York | L61: 12180 | M61: East | N61: TEC-AC-10002167 | O61: Technology | P61: Accessories | Q61: Imation 8gb Micro Traveldrive Usb 2.0 Flash Drive | S61: 2 | T61: 0 | U61: 3.3 | V61: =IF(ISBLANK(E61),"UNKNOWN",E61) -> First Class | W61: =IF(ISBLANK(H61),"UNKNOWN",H61) -> Consumer | X61: =CONCATENATE(J61," - ",K61) -> Troy - New York | Y61: =IF(ISBLANK(P61),"UNKNOWN",P61) -> Accessories | Z61: =IF(ISBLANK(R61),ROUND(AVERAGEIF($O$2:$O$600,O61,$R$2:$R$29),0),R61) -> 507 | AA61: =IF(ISBLANK(R61),ROUND(AVERAGEIF($Y$2:$Y$600,Y61,$R$2:$R$29),0),R61) -> 250 | AB61: =AA61*S61 -> 500 | AC61: =AB61*(1-T61) -> 500 | AD61: CA | AE61: =MID(B61,4,4) -> 2016 | AF61: =RIGHT(B61,6) -> 111682
A62: 61 | B62: CA-2016-111682 | C62: 42538 | D62: 42539 | E62: First Class | F62: TB-21055 | G62: Ted Butterfield | H62: Consumer | I62: United States | J62: Troy | K62: New York | L62: 12180 | M62: East | N62: OFF-BI-10001460 | O62: Office Supplies | P62: Binders | Q62: Plastic Binding Combs | R62: 48.48 | S62: 4 | T62: 0.2 | U62: 16.362 | V62: =IF(ISBLANK(E62),"UNKNOWN",E62) -> First Class | W62: =IF(ISBLANK(H62),"UNKNOWN",H62) -> Consumer | X62: =CONCATENATE(J62," - ",K62) -> Troy - New York | Y62: =IF(ISBLANK(P62),"UNKNOWN",P62) -> Binders | Z62: =IF(ISBLANK(R62),ROUND(AVERAGEIF($O$2:$O$600,O62,$R$2:$R$29),0),R62) -> 48.48 | AA62: =IF(ISBLANK(R62),ROUND(AVERAGEIF($Y$2:$Y$600,Y62,$R$2:$R$29),0),R62) -> 48.48 | AB62: =AA62*S62 -> 193.92 | AC62: =AB62*(1-T62) -> 155.136 | AD62: CA | AE62: =MID(B62,4,4) -> 2016 | AF62: =RIGHT(B62,6) -> 111682
A63: 62 | B63: CA-2016-111682 | C63: 42538 | D63: 42539 | E63: First Class | F63: TB-21055 | G63: Ted Butterfield | H63: Consumer | I63: United States | J63: Troy | K63: New York | L63: 12180 | M63: East | N63: OFF-AR-10001868 | O63: Office Supplies | P63: Art | Q63: Prang Dustless Chalk Sticks | R63: 1.68 | S63: 1 | T63: 0 | U63: 0.84 | V63: =IF(ISBLANK(E63),"UNKNOWN",E63) -> First Class | W63: =IF(ISBLANK(H63),"UNKNOWN",H63) -> Consumer | X63: =CONCATENATE(J63," - ",K63) -> Troy - New York | Y63: =IF(ISBLANK(P63),"UNKNOWN",P63) -> Art | Z63: =IF(ISBLANK(R63),ROUND(AVERAGEIF($O$2:$O$600,O63,$R$2:$R$29),0),R63) -> 1.68 | AA63: =IF(ISBLANK(R63),ROUND(AVERAGEIF($Y$2:$Y$600,Y63,$R$2:$R$29),0),R63) -> 1.68 | AB63: =AA63*S63 -> 1.68 | AC63: =AB63*(1-T63) -> 1.68 | AD63: CA | AE63: =MID(B63,4,4) -> 2016 | AF63: =RIGHT(B63,6) -> 111682
A64: 63 | B64: CA-2015-135545 | C64: 42332 | D64: 42338 | E64: Standard Class | F64: KM-16720 | G64: Kunst Miller | H64: Consumer | I64: United States | J64: Los Angeles | K64: California | L64: 90004 | M64: West | N64: TEC-AC-10004633 | O64: Technology | P64: Accessories | Q64: Verbatim 25 GB 6x Blu-ray Single Layer Recordable Disc, 3/Pack | R64: 13.98 | S64: 2 | T64: 0 | U64: 6.1512 | V64: =IF(ISBLANK(E64),"UNKNOWN",E64) -> Standard Class | W64: =IF(ISBLANK(H64),"UNKNOWN",H64) -> Consumer | X64: =CONCATENATE(J64," - ",K64) -> Los Angeles - California | Y64: =IF(ISBLANK(P64),"UNKNOWN",P64) -> Accessories | Z64: =IF(ISBLANK(R64),ROUND(AVERAGEIF($O$2:$O$600,O64,$R$2:$R$29),0),R64) -> 13.98 | AA64: =IF(ISBLANK(R64),ROUND(AVERAGEIF($Y$2:$Y$600,Y64,$R$2:$R$29),0),R64) -> 13.98 | AB64: =AA64*S64 -> 27.96 | AC64: =AB64*(1-T64) -> 27.96 | AD64: CA | AE64: =MID(B64,4,4) -> 2015 | AF64: =RIGHT(B64,6) -> 135545
A65: 64 | B65: CA-2015-135545 | C65: 42332 | D65: 42338 | E65: Standard Class | F65: KM-16720 | G65: Kunst Miller | H65: Consumer | I65: United States | J65: Los Angeles | K65: California | L65: 90004 | M65: West | N65: OFF-BI-10001078 | O65: Office Supplies | P65: Binders | Q65: Acco PRESSTEX Data Binder with Storage Hooks, Dark Blue, 14 7/8" X 11" | R65: 25.824 | S65: 6 | T65: 0.2 | U65: 9.3612 | V65: =IF(ISBLANK(E65),"UNKNOWN",E65) -> Standard Class | W65: =IF(ISBLANK(H65),"UNKNOWN",H65) -> Consumer | X65: =CONCATENATE(J65," - ",K65) -> Los Angeles - California | Y65: =IF(ISBLANK(P65),"UNKNOWN",P65) -> Binders | Z65: =IF(ISBLANK(R65),ROUND(AVERAGEIF($O$2:$O$600,O65,$R$2:$R$29),0),R65) -> 25.824 | AA65: =IF(ISBLANK(R65),ROUND(AVERAGEIF($Y$2:$Y$600,Y65,$R$2:$R$29),0),R65) -> 25.824 | AB65: =AA65*S65 -> 154.944 | AC65: =AB65*(1-T65) -> 123.9552 | AD65: CA | AE65: =MID(B65,4,4) -> 2015 | AF65: =RIGHT(B65,6) -> 135545
A66: 65 | B66: CA-2015-135545 | C66: 42332 | D66: 42338 | E66: Standard Class | F66: KM-16720 | G66: Kunst Miller | H66: Consumer | I66: United States | J66: Los Angeles | K66: California | L66: 90004 | M66: West | N66: OFF-PA-10003892 | O66: Office Supplies | P66: Paper | Q66: Xerox 1943 | R66: 146.73 | S66: 3 | T66: 0 | U66: 68.9631 | V66: =IF(ISBLANK(E66),"UNKNOWN",E66) -> Standard Class | W66: =IF(ISBLANK(H66),"UNKNOWN",H66) -> Consumer | X66: =CONCATENATE(J66," - ",K66) -> Los Angeles - California | Y66: =IF(ISBLANK(P66),"UNKNOWN",P66) -> Paper | Z66: =IF(ISBLANK(R66),ROUND(AVERAGEIF($O$2:$O$600,O66,$R$2:$R$29),0),R66) -> 146.73 | AA66: =IF(ISBLANK(R66),ROUND(AVERAGEIF($Y$2:$Y$600,Y66,$R$2:$R$29),0),R66) -> 146.73 | AB66: =AA66*S66 -> 440.19 | AC66: =AB66*(1-T66) -> 440.19 | AD66: CA | AE66: =MID(B66,4,4) -> 2015 | AF66: =RIGHT(B66,6) -> 135545
A67: 66 | B67: CA-2015-135545 | C67: 42332 | D67: 42338 | E67: Standard Class | F67: KM-16720 | G67: Kunst Miller | H67: Consumer | I67: United States | J67: Los Angeles | K67: California | L67: 90004 | M67: West | N67: FUR-FU-10000397 | O67: Furniture | P67: Furnishings | Q67: Luxo Economy Swing Arm Lamp | R67: 79.76 | S67: 4 | T67: 0 | U67: 22.3328 | V67: =IF(ISBLANK(E67),"UNKNOWN",E67) -> Standard Class | W67: =IF(ISBLANK(H67),"UNKNOWN",H67) -> Consumer | X67: =CONCATENATE(J67," - ",K67) -> Los Angeles - California | Y67: =IF(ISBLANK(P67),"UNKNOWN",P67) -> Furnishings | Z67: =IF(ISBLANK(R67),ROUND(AVERAGEIF($O$2:$O$600,O67,$R$2:$R$29),0),R67) -> 79.76 | AA67: =IF(ISBLANK(R67),ROUND(AVERAGEIF($Y$2:$Y$600,Y67,$R$2:$R$29),0),R67) -> 79.76 | AB67: =AA67*S67 -> 319.04 | AC67: =AB67*(1-T67) -> 319.04 | AD67: CA | AE67: =MID(B67,4,4) -> 2015 | AF67: =RIGHT(B67,6) -> 135545
A68: 67 | B68: US-2015-164175 | C68: 42124 | D68: 42129 | E68: Standard Class | F68: PS-18970 | G68: Paul Stevenson | H68: Home Office | I68: United States | J68: Chicago | K68: Illinois | L68: 60610 | M68: Central | N68: FUR-CH-10001146 | O68: Furniture | P68: Chairs | Q68: Global Value Mid-Back Manager's Chair, Gray | R68: 213.115 | S68: 5 | T68: 0.3 | U68: -15.2225 | V68: =IF(ISBLANK(E68),"UNKNOWN",E68) -> Standard Class | W68: =IF(ISBLANK(H68),"UNKNOWN",H68) -> Home Office | X68: =CONCATENATE(J68," - ",K68) -> Chicago - Illinois | Y68: =IF(ISBLANK(P68),"UNKNOWN",P68) -> Chairs | Z68: =IF(ISBLANK(R68),ROUND(AVERAGEIF($O$2:$O$600,O68,$R$2:$R$29),0),R68) -> 213.115 | AA68: =IF(ISBLANK(R68),ROUND(AVERAGEIF($Y$2:$Y$600,Y68,$R$2:$R$29),0),R68) -> 213.115 | AB68: =AA68*S68 -> 1065.575 | AC68: =AB68*(1-T68) -> 745.9025 | AD68: US | AE68: =MID(B68,4,4) -> 2015 | AF68: =RIGHT(B68,6) -> 164175
A69: 68 | B69: CA-2014-106376 | C69: 41978 | D69: 41983 | E69: Standard Class | F69: BS-11590 | G69: Brendan Sweed | H69: Corporate | I69: United States | J69: Gilbert | K69: Arizona | L69: 85234 | M69: West | N69: OFF-AR-10002671 | O69: Office Supplies | P69: Art | Q69: Hunt BOSTON Model 1606 High-Volume Electric Pencil Sharpener, Beige | R69: 1113.024 | S69: 8 | T69: 0.2 | U69: 111.3024 | V69: =IF(ISBLANK(E69),"UNKNOWN",E69) -> Standard Class | W69: =IF(ISBLANK(H69),"UNKNOWN",H69) -> Corporate | X69: =CONCATENATE(J69," - ",K69) -> Gilbert - Arizona | Y69: =IF(ISBLANK(P69),"UNKNOWN",P69) -> Art | Z69: =IF(ISBLANK(R69),ROUND(AVERAGEIF($O$2:$O$600,O69,$R$2:$R$29),0),R69) -> 1113.024 | AA69: =IF(ISBLANK(R69),ROUND(AVERAGEIF($Y$2:$Y$600,Y69,$R$2:$R$29),0),R69) -> 1113.024 | AB69: =AA69*S69 -> 8904.192 | AC69: =AB69*(1-T69) -> 7123.3536 | AD69: CA | AE69: =MID(B69,4,4) -> 2014 | AF69: =RIGHT(B69,6) -> 106376
A70: 69 | B70: CA-2014-106376 | C70: 41978 | D70: 41983 | E70: Standard Class | F70: BS-11590 | G70: Brendan Sweed | H70: Corporate | I70: United States | J70: Gilbert | K70: Arizona | L70: 85234 | M70: West | N70: TEC-PH-10002726 | O70: Technology | P70: Phones | Q70: netTALK DUO VoIP Telephone Service | R70: 167.968 | S70: 4 | T70: 0.2 | U70: 62.988 | V70: =IF(ISBLANK(E70),"UNKNOWN",E70) -> Standard Class | W70: =IF(ISBLANK(H70),"UNKNOWN",H70) -> Corporate | X70: =CONCATENATE(J70," - ",K70) -> Gilbert - Arizona | Y70: =IF(ISBLANK(P70),"UNKNOWN",P70) -> Phones | Z70: =IF(ISBLANK(R70),ROUND(AVERAGEIF($O$2:$O$600,O70,$R$2:$R$29),0),R70) -> 167.968 | AA70: =IF(ISBLANK(R70),ROUND(AVERAGEIF($Y$2:$Y$600,Y70,$R$2:$R$29),0),R70) -> 167.968 | AB70: =AA70*S70 -> 671.872 | AC70: =AB70*(1-T70) -> 537.4976 | AD70: CA | AE70: =MID(B70,4,4) -> 2014 | AF70: =RIGHT(B70,6) -> 106376
A71: 70 | B71: CA-2016-119823 | C71: 42525 | D71: 42527 | E71: First Class | F71: KD-16270 | G71: Karen Daniels | H71: Consumer | I71: United States | J71: Springfield | K71: Virginia | L71: 22153 | M71: South | N71: OFF-PA-10000482 | O71: Office Supplies | P71: Paper | Q71: Snap-A-Way Black Print Carbonless Ruled Speed Letter, Triplicate | R71: 75.88 | S71: 2 | T71: 0 | U71: 35.6636 | V71: =IF(ISBLANK(E71),"UNKNOWN",E71) -> First Class | W71: =IF(ISBLANK(H71),"UNKNOWN",H71) -> Consumer | X71: =CONCATENATE(J71," - ",K71) -> Springfield - Virginia | Y71: =IF(ISBLANK(P71),"UNKNOWN",P71) -> Paper | Z71: =IF(ISBLANK(R71),ROUND(AVERAGEIF($O$2:$O$600,O71,$R$2:$R$29),0),R71) -> 75.88 | AA71: =IF(ISBLANK(R71),ROUND(AVERAGEIF($Y$2:$Y$600,Y71,$R$2:$R$29),0),R71) -> 75.88 | AB71: =AA71*S71 -> 151.76 | AC71: =AB71*(1-T71) -> 151.76 | AD71: CA | AE71: =MID(B71,4,4) -> 2016 | AF71: =RIGHT(B71,6) -> 119823
A72: 71 | B72: CA-2016-106075 | C72: 42631 | D72: 42636 | E72: Standard Class | F72: HM-14980 | G72: Henry MacAllister | H72: Consumer | I72: United States | J72: New York City | K72: New York | L72: 10009 | M72: East | N72: OFF-BI-10004654 | O72: Office Supplies | P72: Binders | Q72: Avery Binding System Hidden Tab Executive Style Index Sets | R72: 4.616 | S72: 1 | T72: 0.2 | U72: 1.731 | V72: =IF(ISBLANK(E72),"UNKNOWN",E72) -> Standard Class | W72: =IF(ISBLANK(H72),"UNKNOWN",H72) -> Consumer | X72: =CONCATENATE(J72," - ",K72) -> New York City - New York | Y72: =IF(ISBLANK(P72),"UNKNOWN",P72) -> Binders | Z72: =IF(ISBLANK(R72),ROUND(AVERAGEIF($O$2:$O$600,O72,$R$2:$R$29),0),R72) -> 4.616 | AA72: =IF(ISBLANK(R72),ROUND(AVERAGEIF($Y$2:$Y$600,Y72,$R$2:$R$29),0),R72) -> 4.616 | AB72: =AA72*S72 -> 4.616 | AC72: =AB72*(1-T72) -> 3.6928 | AD72: CA | AE72: =MID(B72,4,4) -> 2016 | AF72: =RIGHT(B72,6) -> 106075
A73: 72 | B73: CA-2017-114440 | C73: 42992 | D73: 42995 | E73: Second Class | F73: TB-21520 | G73: Tracy Blumstein | H73: Consumer | I73: United States | J73: Jackson | K73: Michigan | L73: 49201 | M73: Central | N73: OFF-PA-10004675 | O73: Office Supplies | P73: Paper | Q73: Telephone Message Books with Fax/Mobile Section, 5 1/2" x 3 3/16" | R73: 19.05 | S73: 3 | T73: 0 | U73: 8.763 | V73: =IF(ISBLANK(E73),"UNKNOWN",E73) -> Second Class | W73: =IF(ISBLANK(H73),"UNKNOWN",H73) -> Consumer | X73: =CONCATENATE(J73," - ",K73) -> Jackson - Michigan | Y73: =IF(ISBLANK(P73),"UNKNOWN",P73) -> Paper | Z73: =IF(ISBLANK(R73),ROUND(AVERAGEIF($O$2:$O$600,O73,$R$2:$R$29),0),R73) -> 19.05 | AA73: =IF(ISBLANK(R73),ROUND(AVERAGEIF($Y$2:$Y$600,Y73,$R$2:$R$29),0),R73) -> 19.05 | AB73: =AA73*S73 -> 57.15 | AC73: =AB73*(1-T73) -> 57.15 | AD73: CA | AE73: =MID(B73,4,4) -> 2017 | AF73: =RIGHT(B73,6) -> 114440
... A78: 77 | B78: US-2017-118038 | C78: 43078 | D78: 43080 | E78: First Class | F78: KB-16600 | G78: Ken Brennan | H78: Corporate | I78: United States | J78: Houston | K78: Texas | L78: 77041 | M78: Central | N78: FUR-FU-10000260 | O78: Furniture | P78: Furnishings | Q78: 6" Cubicle Wall Clock, Black | R78: 9.708 | S78: 3 | T78: 0.6 | U78: -5.8248 | V78: =IF(ISBLANK(E78),"UNKNOWN",E78) -> First Class | W78: =IF(ISBLANK(H78),"UNKNOWN",H78) -> Corporate | X78: =CONCATENATE(J78," - ",K78) -> Houston - Texas | Y78: =IF(ISBLANK(P78),"UNKNOWN",P78) -> Furnishings | Z78: =IF(ISBLANK(R78),ROUND(AVERAGEIF($O$2:$O$600,O78,$R$2:$R$29),0),R78) -> 9.708 | AA78: =IF(ISBLANK(R78),ROUND(AVERAGEIF($Y$2:$Y$600,Y78,$R$2:$R$29),0),R78) -> 9.708 | AB78: =AA78*S78 -> 29.124 | AC78: =AB78*(1-T78) -> 11.6496 | AD78: US | AE78: =MID(B78,4,4) -> 2017 | AF78: =RIGHT(B78,6) -> 118038
A79: 78 | B79: US-2017-118038 | C79: 43078 | D79: 43080 | F79: KB-16600 | G79: Ken Brennan | H79: Corporate | I79: United States | J79: Houston | K79: Texas | L79: 77041 | M79: Central | N79: OFF-ST-10000615 | O79: Office Supplies | P79: Storage | Q79: SimpliFile Personal File, Black Granite, 15w x 6-15/16d x 11-1/4h | R79: 27.24 | S79: 3 | T79: 0.2 | U79: 2.724 | V79: =IF(ISBLANK(E79),"UNKNOWN",E79) -> UNKNOWN | W79: =IF(ISBLANK(H79),"UNKNOWN",H79) -> Corporate | X79: =CONCATENATE(J79," - ",K79) -> Houston - Texas | Y79: =IF(ISBLANK(P79),"UNKNOWN",P79) -> Storage | Z79: =IF(ISBLANK(R79),ROUND(AVERAGEIF($O$2:$O$600,O79,$R$2:$R$29),0),R79) -> 27.24 | AA79: =IF(ISBLANK(R79),ROUND(AVERAGEIF($Y$2:$Y$600,Y79,$R$2:$R$29),0),R79) -> 27.24 | AB79: =AA79*S79 -> 81.72 | AC79: =AB79*(1-T79) -> 65.376 | AD79: US | AE79: =MID(B79,4,4) -> 2017 | AF79: =RIGHT(B79,6) -> 118038
A80: 79 | B80: US-2014-147606 | C80: 41969 | D80: 41974 | E80: Second Class | F80: JE-15745 | G80: Joel Eaton | H80: Consumer | I80: United States | J80: Houston | K80: Texas | L80: 77070 | M80: Central | N80: FUR-FU-10003194 | O80: Furniture | P80: Furnishings | Q80: Eldon Expressions Desk Accessory, Wood Pencil Holder, Oak | R80: 19.3 | S80: 5 | T80: 0.6 | U80: -14.475 | V80: =IF(ISBLANK(E80),"UNKNOWN",E80) -> Second Class | W80: =IF(ISBLANK(H80),"UNKNOWN",H80) -> Consumer | X80: =CONCATENATE(J80," - ",K80) -> Houston - Texas | Y80: =IF(ISBLANK(P80),"UNKNOWN",P80) -> Furnishings | Z80: =IF(ISBLANK(R80),ROUND(AVERAGEIF($O$2:$O$600,O80,$R$2:$R$29),0),R80) -> 19.3 | AA80: =IF(ISBLANK(R80),ROUND(AVERAGEIF($Y$2:$Y$600,Y80,$R$2:$R$29),0),R80) -> 19.3 | AB80: =AA80*S80 -> 96.5 | AC80: =AB80*(1-T80) -> 38.6 | AD80: US | AE80: =MID(B80,4,4) -> 2014 | AF80: =RIGHT(B80,6) -> 147606
A81: 80 | B81: CA-2016-127208 | C81: 42533 | D81: 42536 | E81: First Class | F81: SC-20770 | G81: Stewart Carmichael | H81: Corporate | I81: United States | J81: Decatur | K81: Alabama | L81: 35601 | M81: South | N81: OFF-AP-10002118 | O81: Office Supplies | P81: Appliances | Q81: 1.7 Cubic Foot Compact "Cube" Office Refrigerators | R81: 208.16 | S81: 1 | T81: 0 | U81: 56.2032 | V81: =IF(ISBLANK(E81),"UNKNOWN",E81) -> First Class | W81: =IF(ISBLANK(H81),"UNKNOWN",H81) -> Corporate | X81: =CONCATENATE(J81," - ",K81) -> Decatur - Alabama | Y81: =IF(ISBLANK(P81),"UNKNOWN",P81) -> Appliances | Z81: =IF(ISBLANK(R81),ROUND(AVERAGEIF($O$2:$O$600,O81,$R$2:$R$29),0),R81) -> 208.16 | AA81: =IF(ISBLANK(R81),ROUND(AVERAGEIF($Y$2:$Y$600,Y81,$R$2:$R$29),0),R81) -> 208.16 | AB81: =AA81*S81 -> 208.16 | AC81: =AB81*(1-T81) -> 208.16 | AD81: CA | AE81: =MID(B81,4,4) -> 2016 | AF81: =RIGHT(B81,6) -> 127208
A82: 81 | B82: CA-2016-127208 | C82: 42533 | D82: 42536 | E82: First Class | F82: SC-20770 | G82: Stewart Carmichael | H82: Corporate | I82: United States | J82: Decatur | K82: Alabama | L82: 35601 | M82: South | N82: OFF-BI-10002309 | O82: Office Supplies | P82: Binders | Q82: Avery Heavy-Duty EZD Binder With Locking Rings | R82: 16.74 | S82: 3 | T82: 0 | U82: 8.0352 | V82: =IF(ISBLANK(E82),"UNKNOWN",E82) -> First Class | W82: =IF(ISBLANK(H82),"UNKNOWN",H82) -> Corporate | X82: =CONCATENATE(J82," - ",K82) -> Decatur - Alabama | Y82: =IF(ISBLANK(P82),"UNKNOWN",P82) -> Binders | Z82: =IF(ISBLANK(R82),ROUND(AVERAGEIF($O$2:$O$600,O82,$R$2:$R$29),0),R82) -> 16.74 | AA82: =IF(ISBLANK(R82),ROUND(AVERAGEIF($Y$2:$Y$600,Y82,$R$2:$R$29),0),R82) -> 16.74 | AB82: =AA82*S82 -> 50.22 | AC82: =AB82*(1-T82) -> 50.22 | AD82: CA | AE82: =MID(B82,4,4) -> 2016 | AF82: =RIGHT(B82,6) -> 127208
A83: 82 | B83: CA-2014-139451 | C83: 41924 | D83: 41928 | E83: Standard Class | F83: DN-13690 | G83: Duane Noonan | H83: Consumer | I83: United States | J83: San Francisco | K83: California | L83: 94122 | M83: West | N83: OFF-AR-10002053 | O83: Office Supplies | P83: Art | Q83: Premium Writing Pencils, Soft, #2 by Central Association for the Blind | R83: 14.9 | S83: 5 | T83: 0 | U83: 4.172 | V83: =IF(ISBLANK(E83),"UNKNOWN",E83) -> Standard Class | W83: =IF(ISBLANK(H83),"UNKNOWN",H83) -> Consumer | X83: =CONCATENATE(J83," - ",K83) -> San Francisco - California | Y83: =IF(ISBLANK(P83),"UNKNOWN",P83) -> Art | Z83: =IF(ISBLANK(R83),ROUND(AVERAGEIF($O$2:$O$600,O83,$R$2:$R$29),0),R83) -> 14.9 | AA83: =IF(ISBLANK(R83),ROUND(AVERAGEIF($Y$2:$Y$600,Y83,$R$2:$R$29),0),R83) -> 14.9 | AB83: =AA83*S83 -> 74.5 | AC83: =AB83*(1-T83) -> 74.5 | AD83: CA | AE83: =MID(B83,4,4) -> 2014 | AF83: =RIGHT(B83,6) -> 139451
A84: 83 | B84: CA-2014-139451 | C84: 41924 | D84: 41928 | E84: Standard Class | F84: DN-13690 | G84: Duane Noonan | H84: Consumer | I84: United States | J84: San Francisco | K84: California | L84: 94122 | M84: West | N84: OFF-ST-10002370 | O84: Office Supplies | P84: Storage | Q84: Sortfiler Multipurpose Personal File Organizer, Black | R84: 21.39 | S84: 1 | T84: 0 | U84: 6.2031 | V84: =IF(ISBLANK(E84),"UNKNOWN",E84) -> Standard Class | W84: =IF(ISBLANK(H84),"UNKNOWN",H84) -> Consumer | X84: =CONCATENATE(J84," - ",K84) -> San Francisco - California | Y84: =IF(ISBLANK(P84),"UNKNOWN",P84) -> Storage | Z84: =IF(ISBLANK(R84),ROUND(AVERAGEIF($O$2:$O$600,O84,$R$2:$R$29),0),R84) -> 21.39 | AA84: =IF(ISBLANK(R84),ROUND(AVERAGEIF($Y$2:$Y$600,Y84,$R$2:$R$29),0),R84) -> 21.39 | AB84: =AA84*S84 -> 21.39 | AC84: =AB84*(1-T84) -> 21.39 | AD84: CA | AE84: =MID(B84,4,4) -> 2014 | AF84: =RIGHT(B84,6) -> 139451
A85: 84 | B85: CA-2015-149734 | C85: 42250 | D85: 42255 | E85: Standard Class | F85: JC-16105 | G85: Julie Creighton | H85: Corporate | I85: United States | J85: Durham | K85: North Carolina | L85: 27707 | M85: South | N85: OFF-EN-10000927 | O85: Office Supplies | P85: Envelopes | Q85: Jet-Pak Recycled Peel 'N' Seal Padded Mailers | R85: 200.984 | S85: 7 | T85: 0.2 | U85: 62.8075 | V85: =IF(ISBLANK(E85),"UNKNOWN",E85) -> Standard Class | W85: =IF(ISBLANK(H85),"UNKNOWN",H85) -> Corporate | X85: =CONCATENATE(J85," - ",K85) -> Durham - North Carolina | Y85: =IF(ISBLANK(P85),"UNKNOWN",P85) -> Envelopes | Z85: =IF(ISBLANK(R85),ROUND(AVERAGEIF($O$2:$O$600,O85,$R$2:$R$29),0),R85) -> 200.984 | AA85: =IF(ISBLANK(R85),ROUND(AVERAGEIF($Y$2:$Y$600,Y85,$R$2:$R$29),0),R85) -> 200.984 | AB85: =AA85*S85 -> 1406.888 | AC85: =AB85*(1-T85) -> 1125.5104 | AD85: CA | AE85: =MID(B85,4,4) -> 2015 | AF85: =RIGHT(B85,6) -> 149734
A86: 85 | B86: US-2017-119662 | C86: 43052 | D86: 43055 | E86: First Class | F86: CS-12400 | G86: Christopher Schild | H86: Home Office | I86: United States | J86: Chicago | K86: Illinois | L86: 60623 | M86: Central | N86: OFF-ST-10003656 | O86: Office Supplies | P86: Storage | Q86: Safco Industrial Wire Shelving | R86: 230.376 | S86: 3 | T86: 0.2 | U86: -48.9549 | V86: =IF(ISBLANK(E86),"UNKNOWN",E86) -> First Class | W86: =IF(ISBLANK(H86),"UNKNOWN",H86) -> Home Office | X86: =CONCATENATE(J86," - ",K86) -> Chicago - Illinois | Y86: =IF(ISBLANK(P86),"UNKNOWN",P86) -> Storage | Z86: =IF(ISBLANK(R86),ROUND(AVERAGEIF($O$2:$O$600,O86,$R$2:$R$29),0),R86) -> 230.376 | AA86: =IF(ISBLANK(R86),ROUND(AVERAGEIF($Y$2:$Y$600,Y86,$R$2:$R$29),0),R86) -> 230.376 | AB86: =AA86*S86 -> 691.128 | AC86: =AB86*(1-T86) -> 552.9024 | AD86: US | AE86: =MID(B86,4,4) -> 2017 | AF86: =RIGHT(B86,6) -> 119662
A87: 86 | B87: CA-2017-140088 | C87: 42883 | D87: 42885 | E87: Second Class | F87: PO-18865 | G87: Patrick O'Donnell | H87: Consumer | I87: United States | J87: Columbia | K87: South Carolina | L87: 29203 | M87: South | N87: FUR-CH-10000863 | O87: Furniture | P87: Chairs | Q87: Novimex Swivel Fabric Task Chair | R87: 301.96 | S87: 2 | T87: 0 | U87: 33.2156 | V87: =IF(ISBLANK(E87),"UNKNOWN",E87) -> Second Class | W87: =IF(ISBLANK(H87),"UNKNOWN",H87) -> Consumer | X87: =CONCATENATE(J87," - ",K87) -> Columbia - South Carolina | Y87: =IF(ISBLANK(P87),"UNKNOWN",P87) -> Chairs | Z87: =IF(ISBLANK(R87),ROUND(AVERAGEIF($O$2:$O$600,O87,$R$2:$R$29),0),R87) -> 301.96 | AA87: =IF(ISBLANK(R87),ROUND(AVERAGEIF($Y$2:$Y$600,Y87,$R$2:$R$29),0),R87) -> 301.96 | AB87: =AA87*S87 -> 603.92 | AC87: =AB87*(1-T87) -> 603.92 | AD87: CA | AE87: =MID(B87,4,4) -> 2017 | AF87: =RIGHT(B87,6) -> 140088
A88: 87 | B88: CA-2017-155558 | C88: 43034 | D88: 43041 | E88: Standard Class | F88: PG-18895 | G88: Paul Gonzalez | H88: Consumer | I88: United States | J88: Rochester | K88: Minnesota | L88: 55901 | M88: Central | N88: TEC-AC-10001998 | O88: Technology | P88: Accessories | Q88: Logitech LS21 Speaker System - PC Multimedia - 2.1-CH - Wired | R88: 19.99 | S88: 1 | T88: 0 | U88: 6.7966 | V88: =IF(ISBLANK(E88),"UNKNOWN",E88) -> Standard Class | W88: =IF(ISBLANK(H88),"UNKNOWN",H88) -> Consumer | X88: =CONCATENATE(J88," - ",K88) -> Rochester - Minnesota | Y88: =IF(ISBLANK(P88),"UNKNOWN",P88) -> Accessories | Z88: =IF(ISBLANK(R88),ROUND(AVERAGEIF($O$2:$O$600,O88,$R$2:$R$29),0),R88) -> 19.99 | AA88: =IF(ISBLANK(R88),ROUND(AVERAGEIF($Y$2:$Y$600,Y88,$R$2:$R$29),0),R88) -> 19.99 | AB88: =AA88*S88 -> 19.99 | AC88: =AB88*(1-T88) -> 19.99 | AD88: CA | AE88: =MID(B88,4,4) -> 2017 | AF88: =RIGHT(B88,6) -> 155558
A89: 88 | B89: CA-2017-155558 | C89: 43034 | D89: 43041 | E89: Standard Class | F89: PG-18895 | G89: Paul Gonzalez | H89: Consumer | I89: United States | J89: Rochester | K89: Minnesota | L89: 55901 | M89: Central | N89: OFF-LA-10000134 | O89: Office Supplies | P89: Labels | Q89: Avery 511 | R89: 6.16 | S89: 2 | T89: 0 | U89: 2.9568 | V89: =IF(ISBLANK(E89),"UNKNOWN",E89) -> Standard Class | W89: =IF(ISBLANK(H89),"UNKNOWN",H89) -> Consumer | X89: =CONCATENATE(J89," - ",K89) -> Rochester - Minnesota | Y89: =IF(ISBLANK(P89),"UNKNOWN",P89) -> Labels | Z89: =IF(ISBLANK(R89),ROUND(AVERAGEIF($O$2:$O$600,O89,$R$2:$R$29),0),R89) -> 6.16 | AA89: =IF(ISBLANK(R89),ROUND(AVERAGEIF($Y$2:$Y$600,Y89,$R$2:$R$29),0),R89) -> 6.16 | AB89: =AA89*S89 -> 12.32 | AC89: =AB89*(1-T89) -> 12.32 | AD89: CA | AE89: =MID(B89,4,4) -> 2017 | AF89: =RIGHT(B89,6) -> 155558
A90: 89 | B90: CA-2016-159695 | C90: 42465 | D90: 42470 | E90: Second Class | F90: GM-14455 | G90: Gary Mitchum | H90: Home Office | I90: United States | J90: Houston | K90: Texas | L90: 77095 | M90: Central | N90: OFF-ST-10003442 | O90: Office Supplies | P90: Storage | Q90: Eldon Portable Mobile Manager | R90: 158.368 | S90: 7 | T90: 0.2 | U90: 13.8572 | V90: =IF(ISBLANK(E90),"UNKNOWN",E90) -> Second Class | W90: =IF(ISBLANK(H90),"UNKNOWN",H90) -> Home Office | X90: =CONCATENATE(J90," - ",K90) -> Houston - Texas | Y90: =IF(ISBLANK(P90),"UNKNOWN",P90) -> Storage | Z90: =IF(ISBLANK(R90),ROUND(AVERAGEIF($O$2:$O$600,O90,$R$2:$R$29),0),R90) -> 158.368 | AA90: =IF(ISBLANK(R90),ROUND(AVERAGEIF($Y$2:$Y$600,Y90,$R$2:$R$29),0),R90) -> 158.368 | AB90: =AA90*S90 -> 1108.576 | AC90: =AB90*(1-T90) -> 886.8608 | AD90: CA | AE90: =MID(B90,4,4) -> 2016 | AF90: =RIGHT(B90,6) -> 159695
A91: 90 | B91: CA-2016-109806 | C91: 42630 | D91: 42635 | E91: Standard Class | F91: JS-15685 | G91: Jim Sink | H91: Corporate | I91: United States | J91: Los Angeles | K91: California | L91: 90036 | M91: West | N91: OFF-AR-10004930 | O91: Office Supplies | P91: Art | Q91: Turquoise Lead Holder with Pocket Clip | R91: 20.1 | S91: 3 | T91: 0 | U91: 6.633 | V91: =IF(ISBLANK(E91),"UNKNOWN",E91) -> Standard Class | W91: =IF(ISBLANK(H91),"UNKNOWN",H91) -> Corporate | X91: =CONCATENATE(J91," - ",K91) -> Los Angeles - California | Y91: =IF(ISBLANK(P91),"UNKNOWN",P91) -> Art | Z91: =IF(ISBLANK(R91),ROUND(AVERAGEIF($O$2:$O$600,O91,$R$2:$R$29),0),R91) -> 20.1 | AA91: =IF(ISBLANK(R91),ROUND(AVERAGEIF($Y$2:$Y$600,Y91,$R$2:$R$29),0),R91) -> 20.1 | AB91: =AA91*S91 -> 60.3 | AC91: =AB91*(1-T91) -> 60.3 | AD91: CA | AE91: =MID(B91,4,4) -> 2016 | AF91: =RIGHT(B91,6) -> 109806
A92: 91 | B92: CA-2016-109806 | C92: 42630 | D92: 42635 | E92: Standard Class | F92: JS-15685 | G92: Jim Sink | H92: Corporate | I92: United States | J92: Los Angeles | K92: California | L92: 90036 | M92: West | N92: TEC-PH-10004093 | O92: Technology | P92: Phones | Q92: Panasonic Kx-TS550 | R92: 73.584 | S92: 2 | T92: 0.2 | U92: 8.2782 | V92: =IF(ISBLANK(E92),"UNKNOWN",E92) -> Standard Class | W92: =IF(ISBLANK(H92),"UNKNOWN",H92) -> Corporate | X92: =CONCATENATE(J92," - ",K92) -> Los Angeles - California | Y92: =IF(ISBLANK(P92),"UNKNOWN",P92) -> Phones | Z92: =IF(ISBLANK(R92),ROUND(AVERAGEIF($O$2:$O$600,O92,$R$2:$R$29),0),R92) -> 73.584 | AA92: =IF(ISBLANK(R92),ROUND(AVERAGEIF($Y$2:$Y$600,Y92,$R$2:$R$29),0),R92) -> 73.584 | AB92: =AA92*S92 -> 147.168 | AC92: =AB92*(1-T92) -> 117.7344 | AD92: CA | AE92: =MID(B92,4,4) -> 2016 | AF92: =RIGHT(B92,6) -> 109806
A93: 92 | B93: CA-2016-109806 | C93: 42630 | D93: 42635 | E93: Standard Class | F93: JS-15685 | G93: Jim Sink | I93: United States | J93: Los Angeles | K93: California | L93: 90036 | M93: West | N93: OFF-PA-10000304 | O93: Office Supplies | P93: Paper | Q93: Xerox 1995 | R93: 6.48 | S93: 1 | T93: 0 | U93: 3.1104 | V93: =IF(ISBLANK(E93),"UNKNOWN",E93) -> Standard Class | W93: =IF(ISBLANK(H93),"UNKNOWN",H93) -> UNKNOWN | X93: =CONCATENATE(J93," - ",K93) -> Los Angeles - California | Y93: =IF(ISBLANK(P93),"UNKNOWN",P93) -> Paper | Z93: =IF(ISBLANK(R93),ROUND(AVERAGEIF($O$2:$O$600,O93,$R$2:$R$29),0),R93) -> 6.48 | AA93: =IF(ISBLANK(R93),ROUND(AVERAGEIF($Y$2:$Y$600,Y93,$R$2:$R$29),0),R93) -> 6.48 | AB93: =AA93*S93 -> 6.48 | AC93: =AB93*(1-T93) -> 6.48 | AD93: CA | AE93: =MID(B93,4,4) -> 2016 | AF93: =RIGHT(B93,6) -> 109806
A94: 93 | B94: CA-2015-149587 | C94: 42035 | D94: 42040 | E94: Second Class | F94: KB-16315 | G94: Karl Braun | H94: Consumer | I94: United States | J94: Minneapolis | K94: Minnesota | L94: 55407 | M94: Central | N94: OFF-PA-10003177 | O94: Office Supplies | P94: Paper | Q94: Xerox 1999 | R94: 12.96 | S94: 2 | T94: 0 | U94: 6.2208 | V94: =IF(ISBLANK(E94),"UNKNOWN",E94) -> Second Class | W94: =IF(ISBLANK(H94),"UNKNOWN",H94) -> Consumer | X94: =CONCATENATE(J94," - ",K94) -> Minneapolis - Minnesota | Y94: =IF(ISBLANK(P94),"UNKNOWN",P94) -> Paper | Z94: =IF(ISBLANK(R94),ROUND(AVERAGEIF($O$2:$O$600,O94,$R$2:$R$29),0),R94) -> 12.96 | AA94: =IF(ISBLANK(R94),ROUND(AVERAGEIF($Y$2:$Y$600,Y94,$R$2:$R$29),0),R94) -> 12.96 | AB94: =AA94*S94 -> 25.92 | AC94: =AB94*(1-T94) -> 25.92 | AD94: CA | AE94: =MID(B94,4,4) -> 2015 | AF94: =RIGHT(B94,6) -> 149587
A95: 94 | B95: CA-2015-149587 | C95: 42035 | D95: 42040 | E95: Second Class | F95: KB-16315 | G95: Karl Braun | H95: Consumer | I95: United States | J95: Minneapolis | K95: Minnesota | L95: 55407 | M95: Central | N95: FUR-FU-10003799 | O95: Furniture | P95: Furnishings | Q95: Seth Thomas 13 1/2" Wall Clock | R95: 53.34 | S95: 3 | T95: 0 | U95: 16.5354 | V95: =IF(ISBLANK(E95),"UNKNOWN",E95) -> Second Class | W95: =IF(ISBLANK(H95),"UNKNOWN",H95) -> Consumer | X95: =CONCATENATE(J95," - ",K95) -> Minneapolis - Minnesota | Y95: =IF(ISBLANK(P95),"UNKNOWN",P95) -> Furnishings | Z95: =IF(ISBLANK(R95),ROUND(AVERAGEIF($O$2:$O$600,O95,$R$2:$R$29),0),R95) -> 53.34 | AA95: =IF(ISBLANK(R95),ROUND(AVERAGEIF($Y$2:$Y$600,Y95,$R$2:$R$29),0),R95) -> 53.34 | AB95: =AA95*S95 -> 160.02 | AC95: =AB95*(1-T95) -> 160.02 | AD95: CA | AE95: =MID(B95,4,4) -> 2015 | AF95: =RIGHT(B95,6) -> 149587
A96: 95 | B96: CA-2015-149587 | C96: 42035 | D96: 42040 | E96: Second Class | F96: KB-16315 | G96: Karl Braun | H96: Consumer | I96: United States | J96: Minneapolis | K96: Minnesota | L96: 55407 | M96: Central | N96: OFF-BI-10002852 | O96: Office Supplies | P96: Binders | Q96: Ibico Standard Transparent Covers | R96: 32.96 | S96: 2 | T96: 0 | U96: 16.1504 | V96: =IF(ISBLANK(E96),"UNKNOWN",E96) -> Second Class | W96: =IF(ISBLANK(H96),"UNKNOWN",H96) -> Consumer | X96: =CONCATENATE(J96," - ",K96) -> Minneapolis - Minnesota | Y96: =IF(ISBLANK(P96),"UNKNOWN",P96) -> Binders | Z96: =IF(ISBLANK(R96),ROUND(AVERAGEIF($O$2:$O$600,O96,$R$2:$R$29),0),R96) -> 32.96 | AA96: =IF(ISBLANK(R96),ROUND(AVERAGEIF($Y$2:$Y$600,Y96,$R$2:$R$29),0),R96) -> 32.96 | AB96: =AA96*S96 -> 65.92 | AC96: =AB96*(1-T96) -> 65.92 | AD96: CA | AE96: =MID(B96,4,4) -> 2015 | AF96: =RIGHT(B96,6) -> 149587
A97: 96 | B97: US-2017-109484 | C97: 43045 | D97: 43051 | E97: Standard Class | F97: RB-19705 | G97: Roger Barcio | H97: Home Office | I97: United States | J97: Portland | K97: Oregon | L97: 97206 | M97: West | N97: OFF-BI-10004738 | O97: Office Supplies | P97: Binders | Q97: Flexible Leather- Look Classic Collection Ring Binder | R97: 5.682 | S97: 1 | T97: 0.7 | U97: -3.788 | V97: =IF(ISBLANK(E97),"UNKNOWN",E97) -> Standard Class | W97: =IF(ISBLANK(H97),"UNKNOWN",H97) -> Home Office | X97: =CONCATENATE(J97," - ",K97) -> Portland - Oregon | Y97: =IF(ISBLANK(P97),"UNKNOWN",P97) -> Binders | Z97: =IF(ISBLANK(R97),ROUND(AVERAGEIF($O$2:$O$600,O97,$R$2:$R$29),0),R97) -> 5.682 | AA97: =IF(ISBLANK(R97),ROUND(AVERAGEIF($Y$2:$Y$600,Y97,$R$2:$R$29),0),R97) -> 5.682 | AB97: =AA97*S97 -> 5.682 | AC97: =AB97*(1-T97) -> 1.7046 | AD97: US | AE97: =MID(B97,4,4) -> 2017 | AF97: =RIGHT(B97,6) -> 109484
A98: 97 | B98: CA-2017-161018 | C98: 43048 | D98: 43050 | E98: Second Class | F98: PN-18775 | G98: Parhena Norris | H98: Home Office | I98: United States | J98: New York City | K98: New York | L98: 10009 | M98: East | N98: FUR-FU-10000629 | O98: Furniture | P98: Furnishings | Q98: 9-3/4 Diameter Round Wall Clock | R98: 96.53 | S98: 7 | T98: 0 | U98: 40.5426 | V98: =IF(ISBLANK(E98),"UNKNOWN",E98) -> Second Class | W98: =IF(ISBLANK(H98),"UNKNOWN",H98) -> Home Office | X98: =CONCATENATE(J98," - ",K98) -> New York City - New York | Y98: =IF(ISBLANK(P98),"UNKNOWN",P98) -> Furnishings | Z98: =IF(ISBLANK(R98),ROUND(AVERAGEIF($O$2:$O$600,O98,$R$2:$R$29),0),R98) -> 96.53 | AA98: =IF(ISBLANK(R98),ROUND(AVERAGEIF($Y$2:$Y$600,Y98,$R$2:$R$29),0),R98) -> 96.53 | AB98: =AA98*S98 -> 675.71 | AC98: =AB98*(1-T98) -> 675.71 | AD98: CA | AE98: =MID(B98,4,4) -> 2017 | AF98: =RIGHT(B98,6) -> 161018
A99: 98 | B99: CA-2017-157833 | C99: 42903 | D99: 42906 | E99: First Class | F99: KD-16345 | G99: Katherine Ducich | H99: Consumer | I99: United States | J99: San Francisco | K99: California | L99: 94122 | M99: West | N99: OFF-BI-10001721 | O99: Office Supplies | P99: Binders | Q99: Trimflex Flexible Post Binders | R99: 51.312 | S99: 3 | T99: 0.2 | U99: 17.9592 | V99: =IF(ISBLANK(E99),"UNKNOWN",E99) -> First Class | W99: =IF(ISBLANK(H99),"UNKNOWN",H99) -> Consumer | X99: =CONCATENATE(J99," - ",K99) -> San Francisco - California | Y99: =IF(ISBLANK(P99),"UNKNOWN",P99) -> Binders | Z99: =IF(ISBLANK(R99),ROUND(AVERAGEIF($O$2:$O$600,O99,$R$2:$R$29),0),R99) -> 51.312 | AA99: =IF(ISBLANK(R99),ROUND(AVERAGEIF($Y$2:$Y$600,Y99,$R$2:$R$29),0),R99) -> 51.312 | AB99: =AA99*S99 -> 153.936 | AC99: =AB99*(1-T99) -> 123.1488 | AD99: CA | AE99: =MID(B99,4,4) -> 2017 | AF99: =RIGHT(B99,6) -> 157833
A100: 99 | B100: CA-2016-149223 | C100: 42619 | D100: 42624 | E100: Standard Class | F100: ER-13855 | G100: Elpida Rittenbach | H100: Corporate | I100: United States | J100: Saint Paul | K100: Minnesota | L100: 55106 | M100: Central | N100: OFF-AP-10000358 | O100: Office Supplies | P100: Appliances | Q100: Fellowes Basic Home/Office Series Surge Protectors | R100: 77.88 | S100: 6 | T100: 0 | U100: 22.5852 | V100: =IF(ISBLANK(E100),"UNKNOWN",E100) -> Standard Class | W100: =IF(ISBLANK(H100),"UNKNOWN",H100) -> Corporate | X100: =CONCATENATE(J100," - ",K100) -> Saint Paul - Minnesota | Y100: =IF(ISBLANK(P100),"UNKNOWN",P100) -> Appliances | Z100: =IF(ISBLANK(R100),ROUND(AVERAGEIF($O$2:$O$600,O100,$R$2:$R$29),0),R100) -> 77.88 | AA100: =IF(ISBLANK(R100),ROUND(AVERAGEIF($Y$2:$Y$600,Y100,$R$2:$R$29),0),R100) -> 77.88 | AB100: =AA100*S100 -> 467.28 | AC100: =AB100*(1-T100) -> 467.28 | AD100: CA | AE100: =MID(B100,4,4) -> 2016 | AF100: =RIGHT(B100,6) -> 149223
A101: 100 | B101: CA-2016-158568 | C101: 42611 | D101: 42615 | E101: Standard Class | F101: RB-19465 | G101: Rick Bensley | H101: Home Office | I101: United States | J101: Chicago | K101: Illinois | L101: 60610 | M101: Central | N101: OFF-PA-10003256 | O101: Office Supplies | P101: Paper | Q101: Avery Personal Creations Heavyweight Cards | R101: 64.624 | S101: 7 | T101: 0.2 | U101: 22.6184 | V101: =IF(ISBLANK(E101),"UNKNOWN",E101) -> Standard Class | W101: =IF(ISBLANK(H101),"UNKNOWN",H101) -> Home Office | X101: =CONCATENATE(J101," - ",K101) -> Chicago - Illinois | Y101: =IF(ISBLANK(P101),"UNKNOWN",P101) -> Paper | Z101: =IF(ISBLANK(R101),ROUND(AVERAGEIF($O$2:$O$600,O101,$R$2:$R$29),0),R101) -> 64.624 | AA101: =IF(ISBLANK(R101),ROUND(AVERAGEIF($Y$2:$Y$600,Y101,$R$2:$R$29),0),R101) -> 64.624 | AB101: =AA101*S101 -> 452.368 | AC101: =AB101*(1-T101) -> 361.8944 | AD101: CA | AE101: =MID(B101,4,4) -> 2016 | AF101: =RIGHT(B101,6) -> 158568
A102: 101 | B102: CA-2016-158568 | C102: 42611 | D102: 42615 | E102: Standard Class | F102: RB-19465 | G102: Rick Bensley | H102: Home Office | I102: United States | J102: Chicago | K102: Illinois | L102: 60610 | M102: Central | N102: TEC-AC-10001767 | O102: Technology | P102: Accessories | Q102: SanDisk Ultra 64 GB MicroSDHC Class 10 Memory Card | R102: 95.976 | S102: 3 | T102: 0.2 | U102: -10.7973 | V102: =IF(ISBLANK(E102),"UNKNOWN",E102) -> Standard Class | W102: =IF(ISBLANK(H102),"UNKNOWN",H102) -> Home Office | X102: =CONCATENATE(J102," - ",K102) -> Chicago - Illinois | Y102: =IF(ISBLANK(P102),"UNKNOWN",P102) -> Accessories | Z102: =IF(ISBLANK(R102),ROUND(AVERAGEIF($O$2:$O$600,O102,$R$2:$R$29),0),R102) -> 95.976 | AA102: =IF(ISBLANK(R102),ROUND(AVERAGEIF($Y$2:$Y$600,Y102,$R$2:$R$29),0),R102) -> 95.976 | AB102: =AA102*S102 -> 287.928 | AC102: =AB102*(1-T102) -> 230.3424 | AD102: CA | AE102: =MID(B102,4,4) -> 2016 | AF102: =RIGHT(B102,6) -> 158568
A103: 102 | B103: CA-2016-158568 | C103: 42611 | D103: 42615 | E103: Standard Class | F103: RB-19465 | G103: Rick Bensley | H103: Home Office | I103: United States | J103: Chicago | K103: Illinois | L103: 60610 | M103: Central | N103: OFF-BI-10002609 | O103: Office Supplies | P103: Binders | Q103: Avery Hidden Tab Dividers for Binding Systems | R103: 1.788 | S103: 3 | T103: 0.8 | U103: -3.0396 | V103: =IF(ISBLANK(E103),"UNKNOWN",E103) -> Standard Class | W103: =IF(ISBLANK(H103),"UNKNOWN",H103) -> Home Office | X103: =CONCATENATE(J103," - ",K103) -> Chicago - Illinois | Y103: =IF(ISBLANK(P103),"UNKNOWN",P103) -> Binders | Z103: =IF(ISBLANK(R103),ROUND(AVERAGEIF($O$2:$O$600,O103,$R$2:$R$29),0),R103) -> 1.788 | AA103: =IF(ISBLANK(R103),ROUND(AVERAGEIF($Y$2:$Y$600,Y103,$R$2:$R$29),0),R103) -> 1.788 | AB103: =AA103*S103 -> 5.364 | AC103: =AB103*(1-T103) -> 1.0728 | AD103: CA | AE103: =MID(B103,4,4) -> 2016 | AF103: =RIGHT(B103,6) -> 158568
A104: 103 | B104: CA-2016-129903 | C104: 42705 | D104: 42708 | E104: Second Class | F104: GZ-14470 | G104: Gary Zandusky | H104: Consumer | I104: United States | J104: Rochester | K104: Minnesota | L104: 55901 | M104: Central | N104: OFF-PA-10004040 | O104: Office Supplies | P104: Paper | Q104: Universal Premium White Copier/Laser Paper (20Lb. and 87 Bright) | R104: 23.92 | S104: 4 | T104: 0 | U104: 11.7208 | V104: =IF(ISBLANK(E104),"UNKNOWN",E104) -> Second Class | W104: =IF(ISBLANK(H104),"UNKNOWN",H104) -> Consumer | X104: =CONCATENATE(J104," - ",K104) -> Rochester - Minnesota | Y104: =IF(ISBLANK(P104),"UNKNOWN",P104) -> Paper | Z104: =IF(ISBLANK(R104),ROUND(AVERAGEIF($O$2:$O$600,O104,$R$2:$R$29),0),R104) -> 23.92 | AA104: =IF(ISBLANK(R104),ROUND(AVERAGEIF($Y$2:$Y$600,Y104,$R$2:$R$29),0),R104) -> 23.92 | AB104: =AA104*S104 -> 95.68 | AC104: =AB104*(1-T104) -> 95.68 | AD104: CA | AE104: =MID(B104,4,4) -> 2016 | AF104: =RIGHT(B104,6) -> 129903
A105: 104 | B105: US-2015-156867 | C105: 42321 | D105: 42325 | E105: Standard Class | F105: LC-16870 | G105: Lena Cacioppo | H105: Consumer | I105: United States | J105: Aurora | K105: Colorado | L105: 80013 | M105: West | N105: TEC-AC-10001552 | O105: Technology | Q105: Logitech K350 2.4Ghz Wireless Keyboard | R105: 238.896 | S105: 6 | T105: 0.2 | U105: -26.8758 | V105: =IF(ISBLANK(E105),"UNKNOWN",E105) -> Standard Class | W105: =IF(ISBLANK(H105),"UNKNOWN",H105) -> Consumer | X105: =CONCATENATE(J105," - ",K105) -> Aurora - Colorado | Y105: =IF(ISBLANK(P105),"UNKNOWN",P105) -> UNKNOWN | Z105: =IF(ISBLANK(R105),ROUND(AVERAGEIF($O$2:$O$600,O105,$R$2:$R$29),0),R105) -> 238.896 | AA105: =IF(ISBLANK(R105),ROUND(AVERAGEIF($Y$2:$Y$600,Y105,$R$2:$R$29),0),R105) -> 238.896 | AB105: =AA105*S105 -> 1433.376 | AC105: =AB105*(1-T105) -> 1146.7008 | AD105: US | AE105: =MID(B105,4,4) -> 2015 | AF105: =RIGHT(B105,6) -> 156867
A106: 105 | B106: US-2015-156867 | C106: 42321 | D106: 42325 | E106: Standard Class | F106: LC-16870 | G106: Lena Cacioppo | H106: Consumer | I106: United States | J106: Aurora | K106: Colorado | L106: 80013 | M106: West | N106: FUR-FU-10004006 | O106: Furniture | P106: Furnishings | Q106: Deflect-o DuraMat Lighweight, Studded, Beveled Mat for Low Pile Carpeting | R106: 102.36 | S106: 3 | T106: 0.2 | U106: -3.8385 | V106: =IF(ISBLANK(E106),"UNKNOWN",E106) -> Standard Class | W106: =IF(ISBLANK(H106),"UNKNOWN",H106) -> Consumer | X106: =CONCATENATE(J106," - ",K106) -> Aurora - Colorado | Y106: =IF(ISBLANK(P106),"UNKNOWN",P106) -> Furnishings | Z106: =IF(ISBLANK(R106),ROUND(AVERAGEIF($O$2:$O$600,O106,$R$2:$R$29),0),R106) -> 102.36 | AA106: =IF(ISBLANK(R106),ROUND(AVERAGEIF($Y$2:$Y$600,Y106,$R$2:$R$29),0),R106) -> 102.36 | AB106: =AA106*S106 -> 307.08 | AC106: =AB106*(1-T106) -> 245.664 | AD106: US | AE106: =MID(B106,4,4) -> 2015 | AF106: =RIGHT(B106,6) -> 156867
A107: 106 | B107: US-2015-156867 | C107: 42321 | D107: 42325 | E107: Standard Class | F107: LC-16870 | G107: Lena Cacioppo | H107: Consumer | I107: United States | J107: Aurora | K107: Colorado | L107: 80013 | M107: West | N107: OFF-BI-10002794 | O107: Office Supplies | P107: Binders | Q107: Avery Trapezoid Ring Binder, 3" Capacity, Black, 1040 sheets | R107: 36.882 | S107: 3 | T107: 0.7 | U107: -25.8174 | V107: =IF(ISBLANK(E107),"UNKNOWN",E107) -> Standard Class | W107: =IF(ISBLANK(H107),"UNKNOWN",H107) -> Consumer | X107: =CONCATENATE(J107," - ",K107) -> Aurora - Colorado | Y107: =IF(ISBLANK(P107),"UNKNOWN",P107) -> Binders | Z107: =IF(ISBLANK(R107),ROUND(AVERAGEIF($O$2:$O$600,O107,$R$2:$R$29),0),R107) -> 36.882 | AA107: =IF(ISBLANK(R107),ROUND(AVERAGEIF($Y$2:$Y$600,Y107,$R$2:$R$29),0),R107) -> 36.882 | AB107: =AA107*S107 -> 110.646 | AC107: =AB107*(1-T107) -> 33.1938 | AD107: US | AE107: =MID(B107,4,4) -> 2015 | AF107: =RIGHT(B107,6) -> 156867
A108: 107 | B108: CA-2017-119004 | C108: 43062 | D108: 43067 | E108: Standard Class | F108: JM-15250 | G108: Janet Martin | H108: Consumer | I108: United States | J108: Charlotte | K108: North Carolina | L108: 28205 | M108: South | N108: TEC-AC-10003499 | O108: Technology | P108: Accessories | Q108: Memorex Mini Travel Drive 8 GB USB 2.0 Flash Drive | R108: 74.112 | S108: 8 | T108: 0.2 | U108: 17.6016 | V108: =IF(ISBLANK(E108),"UNKNOWN",E108) -> Standard Class | W108: =IF(ISBLANK(H108),"UNKNOWN",H108) -> Consumer | X108: =CONCATENATE(J108," - ",K108) -> Charlotte - North Carolina | Y108: =IF(ISBLANK(P108),"UNKNOWN",P108) -> Accessories | Z108: =IF(ISBLANK(R108),ROUND(AVERAGEIF($O$2:$O$600,O108,$R$2:$R$29),0),R108) -> 74.112 | AA108: =IF(ISBLANK(R108),ROUND(AVERAGEIF($Y$2:$Y$600,Y108,$R$2:$R$29),0),R108) -> 74.112 | AB108: =AA108*S108 -> 592.896 | AC108: =AB108*(1-T108) -> 474.3168 | AD108: CA | AE108: =MID(B108,4,4) -> 2017 | AF108: =RIGHT(B108,6) -> 119004
A109: 108 | B109: CA-2017-119004 | C109: 43062 | D109: 43067 | E109: Standard Class | F109: JM-15250 | G109: Janet Martin | H109: Consumer | I109: United States | J109: Charlotte | K109: North Carolina | L109: 28205 | M109: South | N109: TEC-PH-10002844 | O109: Technology | P109: Phones | Q109: Speck Products Candyshell Flip Case | R109: 27.992 | S109: 1 | T109: 0.2 | U109: 2.0994 | V109: =IF(ISBLANK(E109),"UNKNOWN",E109) -> Standard Class | W109: =IF(ISBLANK(H109),"UNKNOWN",H109) -> Consumer | X109: =CONCATENATE(J109," - ",K109) -> Charlotte - North Carolina | Y109: =IF(ISBLANK(P109),"UNKNOWN",P109) -> Phones | Z109: =IF(ISBLANK(R109),ROUND(AVERAGEIF($O$2:$O$600,O109,$R$2:$R$29),0),R109) -> 27.992 | AA109: =IF(ISBLANK(R109),ROUND(AVERAGEIF($Y$2:$Y$600,Y109,$R$2:$R$29),0),R109) -> 27.992 | AB109: =AA109*S109 -> 27.992 | AC109: =AB109*(1-T109) -> 22.3936 | AD109: CA | AE109: =MID(B109,4,4) -> 2017 | AF109: =RIGHT(B109,6) -> 119004
A110: 109 | B110: CA-2017-119004 | C110: 43062 | D110: 43067 | E110: Standard Class | F110: JM-15250 | G110: Janet Martin | H110: Consumer | I110: United States | J110: Charlotte | K110: North Carolina | L110: 28205 | M110: South | N110: OFF-AR-10000390 | O110: Office Supplies | P110: Art | Q110: Newell Chalk Holder | R110: 3.304 | S110: 1 | T110: 0.2 | U110: 1.0738 | V110: =IF(ISBLANK(E110),"UNKNOWN",E110) -> Standard Class | W110: =IF(ISBLANK(H110),"UNKNOWN",H110) -> Consumer | X110: =CONCATENATE(J110," - ",K110) -> Charlotte - North Carolina | Y110: =IF(ISBLANK(P110),"UNKNOWN",P110) -> Art | Z110: =IF(ISBLANK(R110),ROUND(AVERAGEIF($O$2:$O$600,O110,$R$2:$R$29),0),R110) -> 3.304 | AA110: =IF(ISBLANK(R110),ROUND(AVERAGEIF($Y$2:$Y$600,Y110,$R$2:$R$29),0),R110) -> 3.304 | AB110: =AA110*S110 -> 3.304 | AC110: =AB110*(1-T110) -> 2.6432 | AD110: CA | AE110: =MID(B110,4,4) -> 2017 | AF110: =RIGHT(B110,6) -> 119004
A111: 110 | B111: CA-2015-129476 | C111: 42292 | D111: 42297 | E111: Standard Class | F111: PA-19060 | G111: Pete Armstrong | H111: Home Office | I111: United States | J111: Orland Park | K111: Illinois | L111: 60462 | M111: Central | N111: TEC-AC-10000844 | O111: Technology | P111: Accessories | Q111: Logitech Gaming G510s - Keyboard | R111: 339.96 | S111: 5 | T111: 0.2 | U111: 67.992 | V111: =IF(ISBLANK(E111),"UNKNOWN",E111) -> Standard Class | W111: =IF(ISBLANK(H111),"UNKNOWN",H111) -> Home Office | X111: =CONCATENATE(J111," - ",K111) -> Orland Park - Illinois | Y111: =IF(ISBLANK(P111),"UNKNOWN",P111) -> Accessories | Z111: =IF(ISBLANK(R111),ROUND(AVERAGEIF($O$2:$O$600,O111,$R$2:$R$29),0),R111) -> 339.96 | AA111: =IF(ISBLANK(R111),ROUND(AVERAGEIF($Y$2:$Y$600,Y111,$R$2:$R$29),0),R111) -> 339.96 | AB111: =AA111*S111 -> 1699.8 | AC111: =AB111*(1-T111) -> 1359.84 | AD111: CA | AE111: =MID(B111,4,4) -> 2015 | AF111: =RIGHT(B111,6) -> 129476
...

Sheet Cleaned Dataset
A1: SuperStore Sales Analysis
A2: Row ID | B2: Product ID | C2: Order ID | D2: CustomerName | E2: Customer ID | F2: Segment | G2: Order Date | H2: Country | I2: City and State | J2: Region | K2: Category | L2: Sub-Category | M2: Product Name | N2: Sales | O2: Quantity | P2: Discount | Q2: Profit | R2: Total Sales | S2: Revenue
A3: 1 | B3: FUR-BO-10001798 | C3: =_xlfn.XLOOKUP(B3,DataSet!$N$2:$N$600,DataSet!$AF$2:$AF$600,0) -> 152156 | D3: =_xlfn.XLOOKUP(B3,DataSet!$N$2:$N$600,DataSet!$G$2:$G$600,0) -> Claire Gute | E3: =_xlfn.XLOOKUP(B3,DataSet!$N$2:$N$600,DataSet!$F$2:$F$600,0) -> CG-12520 | F3: =_xlfn.XLOOKUP(B3,DataSet!$N$2:$N$600,DataSet!$W$2:$W$600,0) -> Consumer | G3: =_xlfn.XLOOKUP(B3,DataSet!$N$2:$N$600,DataSet!$C$2:$C$600,0) -> 42682 | H3: =_xlfn.XLOOKUP(B3,DataSet!$N$2:$N$600,DataSet!$I$2:$I$600,0) -> United States | I3: =_xlfn.XLOOKUP(B3,DataSet!$N$2:$N$600,DataSet!$X$2:$X$600,0) -> Henderson - Kentucky | J3: =_xlfn.XLOOKUP(B3,DataSet!$N$2:$N$600,DataSet!$M$2:$M$600,0) -> South | K3: =_xlfn.XLOOKUP(B3,DataSet!$N$2:$N$600,DataSet!$O$2:$O$600,0) -> Furniture | L3: =_xlfn.XLOOKUP(B3,DataSet!$N$2:$N$600,DataSet!$Y$2:$Y$600,0) -> Bookcases | M3: =_xlfn.XLOOKUP(B3,DataSet!$N$2:$N$600,DataSet!$Q$2:$Q$600,0) -> Bush Somerset Collection Bookcase | N3: =_xlfn.XLOOKUP(B3,DataSet!$N$2:$N$600,DataSet!$AA$2:$AA$600,0) -> 261.96 | O3: =_xlfn.XLOOKUP(B3,DataSet!$N$2:$N$600,DataSet!$S$2:$S$600,0) -> 2 | P3: =_xlfn.XLOOKUP(B3,DataSet!$N$2:$N$600,DataSet!$T$2:$T$600,0) -> 0 | Q3: =_xlfn.XLOOKUP(B3,DataSet!$N$2:$N$600,DataSet!$U$2:$U$600,0) -> 41.9136 | R3: =_xlfn.XLOOKUP(B3,DataSet!$N$2:$N$600,DataSet!$AB$2:$AB$600,0) -> 523.92 | S3: =_xlfn.XLOOKUP(B3,DataSet!$N$2:$N$600,DataSet!$AC$2:$AC$600,0) -> 523.92
A4: 2 | B4: FUR-CH-10000454 | C4: =_xlfn.XLOOKUP(B4,DataSet!$N$2:$N$600,DataSet!$AF$2:$AF$600,0) -> 152156 | D4: =_xlfn.XLOOKUP(B4,DataSet!$N$2:$N$600,DataSet!$G$2:$G$600,0) -> Claire Gute | E4: =_xlfn.XLOOKUP(B4,DataSet!$N$2:$N$600,DataSet!$F$2:$F$600,0) -> CG-12520 | F4: =_xlfn.XLOOKUP(B4,DataSet!$N$2:$N$600,DataSet!$W$2:$W$600,0) -> Consumer | G4: =_xlfn.XLOOKUP(B4,DataSet!$N$2:$N$600,DataSet!$C$2:$C$600,0) -> 42682 | H4: =_xlfn.XLOOKUP(B4,DataSet!$N$2:$N$600,DataSet!$I$2:$I$600,0) -> United States | I4: =_xlfn.XLOOKUP(B4,DataSet!$N$2:$N$600,DataSet!$X$2:$X$600,0) -> Henderson - Kentucky | J4: =_xlfn.XLOOKUP(B4,DataSet!$N$2:$N$600,DataSet!$M$2:$M$600,0) -> South | K4: =_xlfn.XLOOKUP(B4,DataSet!$N$2:$N$600,DataSet!$O$2:$O$600,0) -> Furniture | L4: =_xlfn.XLOOKUP(B4,DataSet!$N$2:$N$600,DataSet!$Y$2:$Y$600,0) -> Chairs | M4: =_xlfn.XLOOKUP(B4,DataSet!$N$2:$N$600,DataSet!$Q$2:$Q$600,0) -> Hon Deluxe Fabric Upholstered Stacking Chairs, Rounded Back | N4: =_xlfn.XLOOKUP(B4,DataSet!$N$2:$N$600,DataSet!$AA$2:$AA$600,0) -> 731.94 | O4: =_xlfn.XLOOKUP(B4,DataSet!$N$2:$N$600,DataSet!$S$2:$S$600,0) -> 3 | P4: =_xlfn.XLOOKUP(B4,DataSet!$N$2:$N$600,DataSet!$T$2:$T$600,0) -> 0 | Q4: =_xlfn.XLOOKUP(B4,DataSet!$N$2:$N$600,DataSet!$U$2:$U$600,0) -> 219.582 | R4: =_xlfn.XLOOKUP(B4,DataSet!$N$2:$N$600,DataSet!$AB$2:$AB$600,0) -> 2195.82 | S4: =_xlfn.XLOOKUP(B4,DataSet!$N$2:$N$600,DataSet!$AC$2:$AC$600,0) -> 2195.82
A5: 3 | B5: OFF-LA-10000240 | C5: =_xlfn.XLOOKUP(B5,DataSet!$N$2:$N$600,DataSet!$AF$2:$AF$600,0) -> 138688 | D5: =_xlfn.XLOOKUP(B5,DataSet!$N$2:$N$600,DataSet!$G$2:$G$600,0) -> Darrin Van Huff | E5: =_xlfn.XLOOKUP(B5,DataSet!$N$2:$N$600,DataSet!$F$2:$F$600,0) -> DV-13045 | F5: =_xlfn.XLOOKUP(B5,DataSet!$N$2:$N$600,DataSet!$W$2:$W$600,0) -> Corporate | G5: =_xlfn.XLOOKUP(B5,DataSet!$N$2:$N$600,DataSet!$C$2:$C$600,0) -> 42533 | H5: =_xlfn.XLOOKUP(B5,DataSet!$N$2:$N$600,DataSet!$I$2:$I$600,0) -> United States | I5: =_xlfn.XLOOKUP(B5,DataSet!$N$2:$N$600,DataSet!$X$2:$X$600,0) -> Los Angeles - California | J5: =_xlfn.XLOOKUP(B5,DataSet!$N$2:$N$600,DataSet!$M$2:$M$600,0) -> West | K5: =_xlfn.XLOOKUP(B5,DataSet!$N$2:$N$600,DataSet!$O$2:$O$600,0) -> Office Supplies | L5: =_xlfn.XLOOKUP(B5,DataSet!$N$2:$N$600,DataSet!$Y$2:$Y$600,0) -> Labels | M5: =_xlfn.XLOOKUP(B5,DataSet!$N$2:$N$600,DataSet!$Q$2:$Q$600,0) -> Self-Adhesive Address Labels for Typewriters by Universal | N5: =_xlfn.XLOOKUP(B5,DataSet!$N$2:$N$600,DataSet!$AA$2:$AA$600,0) -> 14.62 | O5: =_xlfn.XLOOKUP(B5,DataSet!$N$2:$N$600,DataSet!$S$2:$S$600,0) -> 2 | P5: =_xlfn.XLOOKUP(B5,DataSet!$N$2:$N$600,DataSet!$T$2:$T$600,0) -> 0 | Q5: =_xlfn.XLOOKUP(B5,DataSet!$N$2:$N$600,DataSet!$U$2:$U$600,0) -> 6.8714 | R5: =_xlfn.XLOOKUP(B5,DataSet!$N$2:$N$600,DataSet!$AB$2:$AB$600,0) -> 29.24 | S5: =_xlfn.XLOOKUP(B5,DataSet!$N$2:$N$600,DataSet!$AC$2:$AC$600,0) -> 29.24
A6: 4 | B6: FUR-TA-10000577 | C6: =_xlfn.XLOOKUP(B6,DataSet!$N$2:$N$600,DataSet!$AF$2:$AF$600,0) -> 108966 | D6: =_xlfn.XLOOKUP(B6,DataSet!$N$2:$N$600,DataSet!$G$2:$G$600,0) -> Sean O'Donnell | E6: =_xlfn.XLOOKUP(B6,DataSet!$N$2:$N$600,DataSet!$F$2:$F$600,0) -> SO-20335 | F6: =_xlfn.XLOOKUP(B6,DataSet!$N$2:$N$600,DataSet!$W$2:$W$600,0) -> Consumer | G6: =_xlfn.XLOOKUP(B6,DataSet!$N$2:$N$600,DataSet!$C$2:$C$600,0) -> 42288 | H6: =_xlfn.XLOOKUP(B6,DataSet!$N$2:$N$600,DataSet!$I$2:$I$600,0) -> United States | I6: =_xlfn.XLOOKUP(B6,DataSet!$N$2:$N$600,DataSet!$X$2:$X$600,0) -> Fort Lauderdale - Florida | J6: =_xlfn.XLOOKUP(B6,DataSet!$N$2:$N$600,DataSet!$M$2:$M$600,0) -> South | K6: =_xlfn.XLOOKUP(B6,DataSet!$N$2:$N$600,DataSet!$O$2:$O$600,0) -> Furniture | L6: =_xlfn.XLOOKUP(B6,DataSet!$N$2:$N$600,DataSet!$Y$2:$Y$600,0) -> Tables | M6: =_xlfn.XLOOKUP(B6,DataSet!$N$2:$N$600,DataSet!$Q$2:$Q$600,0) -> Bretford CR4500 Series Slim Rectangular Table | N6: =_xlfn.XLOOKUP(B6,DataSet!$N$2:$N$600,DataSet!$AA$2:$AA$600,0) -> 957.5775 | O6: =_xlfn.XLOOKUP(B6,DataSet!$N$2:$N$600,DataSet!$S$2:$S$600,0) -> 5 | P6: =_xlfn.XLOOKUP(B6,DataSet!$N$2:$N$600,DataSet!$T$2:$T$600,0) -> 0.45 | Q6: =_xlfn.XLOOKUP(B6,DataSet!$N$2:$N$600,DataSet!$U$2:$U$600,0) -> -383.031 | R6: =_xlfn.XLOOKUP(B6,DataSet!$N$2:$N$600,DataSet!$AB$2:$AB$600,0) -> 4787.8875 | S6: =_xlfn.XLOOKUP(B6,DataSet!$N$2:$N$600,DataSet!$AC$2:$AC$600,0) -> 2633.3381
A7: 5 | B7: OFF-ST-10000760 | C7: =_xlfn.XLOOKUP(B7,DataSet!$N$2:$N$600,DataSet!$AF$2:$AF$600,0) -> 108966 | D7: =_xlfn.XLOOKUP(B7,DataSet!$N$2:$N$600,DataSet!$G$2:$G$600,0) -> Sean O'Donnell | E7: =_xlfn.XLOOKUP(B7,DataSet!$N$2:$N$600,DataSet!$F$2:$F$600,0) -> SO-20335 | F7: =_xlfn.XLOOKUP(B7,DataSet!$N$2:$N$600,DataSet!$W$2:$W$600,0) -> Consumer | G7: =_xlfn.XLOOKUP(B7,DataSet!$N$2:$N$600,DataSet!$C$2:$C$600,0) -> 42288 | H7: =_xlfn.XLOOKUP(B7,DataSet!$N$2:$N$600,DataSet!$I$2:$I$600,0) -> United States | I7: =_xlfn.XLOOKUP(B7,DataSet!$N$2:$N$600,DataSet!$X$2:$X$600,0) -> Fort Lauderdale - Florida | J7: =_xlfn.XLOOKUP(B7,DataSet!$N$2:$N$600,DataSet!$M$2:$M$600,0) -> South | K7: =_xlfn.XLOOKUP(B7,DataSet!$N$2:$N$600,DataSet!$O$2:$O$600,0) -> Office Supplies | L7: =_xlfn.XLOOKUP(B7,DataSet!$N$2:$N$600,DataSet!$Y$2:$Y$600,0) -> Storage | M7: =_xlfn.XLOOKUP(B7,DataSet!$N$2:$N$600,DataSet!$Q$2:$Q$600,0) -> Eldon Fold 'N Roll Cart System | N7: =_xlfn.XLOOKUP(B7,DataSet!$N$2:$N$600,DataSet!$AA$2:$AA$600,0) -> 22.368 | O7: =_xlfn.XLOOKUP(B7,DataSet!$N$2:$N$600,DataSet!$S$2:$S$600,0) -> 2 | P7: =_xlfn.XLOOKUP(B7,DataSet!$N$2:$N$600,DataSet!$T$2:$T$600,0) -> 0.2 | Q7: =_xlfn.XLOOKUP(B7,DataSet!$N$2:$N$600,DataSet!$U$2:$U$600,0) -> 2.5164 | R7: =_xlfn.XLOOKUP(B7,DataSet!$N$2:$N$600,DataSet!$AB$2:$AB$600,0) -> 44.736 | S7: =_xlfn.XLOOKUP(B7,DataSet!$N$2:$N$600,DataSet!$AC$2:$AC$600,0) -> 35.7888
A8: 6 | B8: FUR-FU-10001487 | C8: =_xlfn.XLOOKUP(B8,DataSet!$N$2:$N$600,DataSet!$AF$2:$AF$600,0) -> 115812 | D8: =_xlfn.XLOOKUP(B8,DataSet!$N$2:$N$600,DataSet!$G$2:$G$600,0) -> Brosina Hoffman | E8: =_xlfn.XLOOKUP(B8,DataSet!$N$2:$N$600,DataSet!$F$2:$F$600,0) -> BH-11710 | F8: =_xlfn.XLOOKUP(B8,DataSet!$N$2:$N$600,DataSet!$W$2:$W$600,0) -> Consumer | G8: =_xlfn.XLOOKUP(B8,DataSet!$N$2:$N$600,DataSet!$C$2:$C$600,0) -> 41799 | H8: =_xlfn.XLOOKUP(B8,DataSet!$N$2:$N$600,DataSet!$I$2:$I$600,0) -> United States | I8: =_xlfn.XLOOKUP(B8,DataSet!$N$2:$N$600,DataSet!$X$2:$X$600,0) -> Los Angeles - California | J8: =_xlfn.XLOOKUP(B8,DataSet!$N$2:$N$600,DataSet!$M$2:$M$600,0) -> West | K8: =_xlfn.XLOOKUP(B8,DataSet!$N$2:$N$600,DataSet!$O$2:$O$600,0) -> Furniture | L8: =_xlfn.XLOOKUP(B8,DataSet!$N$2:$N$600,DataSet!$Y$2:$Y$600,0) -> Furnishings | M8: =_xlfn.XLOOKUP(B8,DataSet!$N$2:$N$600,DataSet!$Q$2:$Q$600,0) -> Eldon Expressions Wood and Plastic Desk Accessories, Cherry Wood | N8: =_xlfn.XLOOKUP(B8,DataSet!$N$2:$N$600,DataSet!$AA$2:$AA$600,0) -> 48.86 | O8: =_xlfn.XLOOKUP(B8,DataSet!$N$2:$N$600,DataSet!$S$2:$S$600,0) -> 7 | P8: =_xlfn.XLOOKUP(B8,DataSet!$N$2:$N$600,DataSet!$T$2:$T$600,0) -> 0 | Q8: =_xlfn.XLOOKUP(B8,DataSet!$N$2:$N$600,DataSet!$U$2:$U$600,0) -> 14.1694 | R8: =_xlfn.XLOOKUP(B8,DataSet!$N$2:$N$600,DataSet!$AB$2:$AB$600,0) -> 342.02 | S8: =_xlfn.XLOOKUP(B8,DataSet!$N$2:$N$600,DataSet!$AC$2:$AC$600,0) -> 342.02
A9: 7 | B9: OFF-AR-10002833 | C9: =_xlfn.XLOOKUP(B9,DataSet!$N$2:$N$600,DataSet!$AF$2:$AF$600,0) -> 115812 | D9: =_xlfn.XLOOKUP(B9,DataSet!$N$2:$N$600,DataSet!$G$2:$G$600,0) -> Brosina Hoffman | E9: =_xlfn.XLOOKUP(B9,DataSet!$N$2:$N$600,DataSet!$F$2:$F$600,0) -> BH-11710 | F9: =_xlfn.XLOOKUP(B9,DataSet!$N$2:$N$600,DataSet!$W$2:$W$600,0) -> Consumer | G9: =_xlfn.XLOOKUP(B9,DataSet!$N$2:$N$600,DataSet!$C$2:$C$600,0) -> 41799 | H9: =_xlfn.XLOOKUP(B9,DataSet!$N$2:$N$600,DataSet!$I$2:$I$600,0) -> United States | I9: =_xlfn.XLOOKUP(B9,DataSet!$N$2:$N$600,DataSet!$X$2:$X$600,0) -> Los Angeles - California | J9: =_xlfn.XLOOKUP(B9,DataSet!$N$2:$N$600,DataSet!$M$2:$M$600,0) -> West | K9: =_xlfn.XLOOKUP(B9,DataSet!$N$2:$N$600,DataSet!$O$2:$O$600,0) -> Office Supplies | L9: =_xlfn.XLOOKUP(B9,DataSet!$N$2:$N$600,DataSet!$Y$2:$Y$600,0) -> Art | M9: =_xlfn.XLOOKUP(B9,DataSet!$N$2:$N$600,DataSet!$Q$2:$Q$600,0) -> Newell 322 | N9: =_xlfn.XLOOKUP(B9,DataSet!$N$2:$N$600,DataSet!$AA$2:$AA$600,0) -> 7.28 | O9: =_xlfn.XLOOKUP(B9,DataSet!$N$2:$N$600,DataSet!$S$2:$S$600,0) -> 4 | P9: =_xlfn.XLOOKUP(B9,DataSet!$N$2:$N$600,DataSet!$T$2:$T$600,0) -> 0 | Q9: =_xlfn.XLOOKUP(B9,DataSet!$N$2:$N$600,DataSet!$U$2:$U$600,0) -> 1.9656 | R9: =_xlfn.XLOOKUP(B9,DataSet!$N$2:$N$600,DataSet!$AB$2:$AB$600,0) -> 29.12 | S9: =_xlfn.XLOOKUP(B9,DataSet!$N$2:$N$600,DataSet!$AC$2:$AC$600,0) -> 29.12
A10: 8 | B10: TEC-PH-10002275 | C10: =_xlfn.XLOOKUP(B10,DataSet!$N$2:$N$600,DataSet!$AF$2:$AF$600,0) -> 115812 | D10: =_xlfn.XLOOKUP(B10,DataSet!$N$2:$N$600,DataSet!$G$2:$G$600,0) -> Brosina Hoffman | E10: =_xlfn.XLOOKUP(B10,DataSet!$N$2:$N$600,DataSet!$F$2:$F$600,0) -> BH-11710 | F10: =_xlfn.XLOOKUP(B10,DataSet!$N$2:$N$600,DataSet!$W$2:$W$600,0) -> Consumer | G10: =_xlfn.XLOOKUP(B10,DataSet!$N$2:$N$600,DataSet!$C$2:$C$600,0) -> 41799 | H10: =_xlfn.XLOOKUP(B10,DataSet!$N$2:$N$600,DataSet!$I$2:$I$600,0) -> United States | I10: =_xlfn.XLOOKUP(B10,DataSet!$N$2:$N$600,DataSet!$X$2:$X$600,0) -> Los Angeles - California | J10: =_xlfn.XLOOKUP(B10,DataSet!$N$2:$N$600,DataSet!$M$2:$M$600,0) -> West | K10: =_xlfn.XLOOKUP(B10,DataSet!$N$2:$N$600,DataSet!$O$2:$O$600,0) -> Technology | L10: =_xlfn.XLOOKUP(B10,DataSet!$N$2:$N$600,DataSet!$Y$2:$Y$600,0) -> Phones | M10: =_xlfn.XLOOKUP(B10,DataSet!$N$2:$N$600,DataSet!$Q$2:$Q$600,0) -> Mitel 5320 IP Phone VoIP phone | N10: =_xlfn.XLOOKUP(B10,DataSet!$N$2:$N$600,DataSet!$AA$2:$AA$600,0) -> 907.152 | O10: =_xlfn.XLOOKUP(B10,DataSet!$N$2:$N$600,DataSet!$S$2:$S$600,0) -> 6 | P10: =_xlfn.XLOOKUP(B10,DataSet!$N$2:$N$600,DataSet!$T$2:$T$600,0) -> 0.2 | Q10: =_xlfn.XLOOKUP(B10,DataSet!$N$2:$N$600,DataSet!$U$2:$U$600,0) -> 90.7152 | R10: =_xlfn.XLOOKUP(B10,DataSet!$N$2:$N$600,DataSet!$AB$2:$AB$600,0) -> 5442.912 | S10: =_xlfn.XLOOKUP(B10,DataSet!$N$2:$N$600,DataSet!$AC$2:$AC$600,0) -> 4354.3296
A11: 9 | B11: OFF-BI-10003910 | C11: =_xlfn.XLOOKUP(B11,DataSet!$N$2:$N$600,DataSet!$AF$2:$AF$600,0) -> 115812 | D11: =_xlfn.XLOOKUP(B11,DataSet!$N$2:$N$600,DataSet!$G$2:$G$600,0) -> Brosina Hoffman | E11: =_xlfn.XLOOKUP(B11,DataSet!$N$2:$N$600,DataSet!$F$2:$F$600,0) -> BH-11710 | F11: =_xlfn.XLOOKUP(B11,DataSet!$N$2:$N$600,DataSet!$W$2:$W$600,0) -> Consumer | G11: =_xlfn.XLOOKUP(B11,DataSet!$N$2:$N$600,DataSet!$C$2:$C$600,0) -> 41799 | H11: =_xlfn.XLOOKUP(B11,DataSet!$N$2:$N$600,DataSet!$I$2:$I$600,0) -> United States | I11: =_xlfn.XLOOKUP(B11,DataSet!$N$2:$N$600,DataSet!$X$2:$X$600,0) -> Los Angeles - California | J11: =_xlfn.XLOOKUP(B11,DataSet!$N$2:$N$600,DataSet!$M$2:$M$600,0) -> West | K11: =_xlfn.XLOOKUP(B11,DataSet!$N$2:$N$600,DataSet!$O$2:$O$600,0) -> Office Supplies | L11: =_xlfn.XLOOKUP(B11,DataSet!$N$2:$N$600,DataSet!$Y$2:$Y$600,0) -> Binders | M11: =_xlfn.XLOOKUP(B11,DataSet!$N$2:$N$600,DataSet!$Q$2:$Q$600,0) -> DXL Angle-View Binders with Locking Rings by Samsill | N11: =_xlfn.XLOOKUP(B11,DataSet!$N$2:$N$600,DataSet!$AA$2:$AA$600,0) -> 18.504 | O11: =_xlfn.XLOOKUP(B11,DataSet!$N$2:$N$600,DataSet!$S$2:$S$600,0) -> 3 | P11: =_xlfn.XLOOKUP(B11,DataSet!$N$2:$N$600,DataSet!$T$2:$T$600,0) -> 0.2 | Q11: =_xlfn.XLOOKUP(B11,DataSet!$N$2:$N$600,DataSet!$U$2:$U$600,0) -> 5.7825 | R11: =_xlfn.XLOOKUP(B11,DataSet!$N$2:$N$600,DataSet!$AB$2:$AB$600,0) -> 55.512 | S11: =_xlfn.XLOOKUP(B11,DataSet!$N$2:$N$600,DataSet!$AC$2:$AC$600,0) -> 44.4096
A12: 10 | B12: OFF-AP-10002892 | C12: =_xlfn.XLOOKUP(B12,DataSet!$N$2:$N$600,DataSet!$AF$2:$AF$600,0) -> 115812 | D12: =_xlfn.XLOOKUP(B12,DataSet!$N$2:$N$600,DataSet!$G$2:$G$600,0) -> Brosina Hoffman | E12: =_xlfn.XLOOKUP(B12,DataSet!$N$2:$N$600,DataSet!$F$2:$F$600,0) -> BH-11710 | F12: =_xlfn.XLOOKUP(B12,DataSet!$N$2:$N$600,DataSet!$W$2:$W$600,0) -> Consumer | G12: =_xlfn.XLOOKUP(B12,DataSet!$N$2:$N$600,DataSet!$C$2:$C$600,0) -> 41799 | H12: =_xlfn.XLOOKUP(B12,DataSet!$N$2:$N$600,DataSet!$I$2:$I$600,0) -> United States | I12: =_xlfn.XLOOKUP(B12,DataSet!$N$2:$N$600,DataSet!$X$2:$X$600,0) -> Los Angeles - California | J12: =_xlfn.XLOOKUP(B12,DataSet!$N$2:$N$600,DataSet!$M$2:$M$600,0) -> West | K12: =_xlfn.XLOOKUP(B12,DataSet!$N$2:$N$600,DataSet!$O$2:$O$600,0) -> Office Supplies | L12: =_xlfn.XLOOKUP(B12,DataSet!$N$2:$N$600,DataSet!$Y$2:$Y$600,0) -> Appliances | M12: =_xlfn.XLOOKUP(B12,DataSet!$N$2:$N$600,DataSet!$Q$2:$Q$600,0) -> Belkin F5C206VTEL 6 Outlet Surge | N12: =_xlfn.XLOOKUP(B12,DataSet!$N$2:$N$600,DataSet!$AA$2:$AA$600,0) -> 114.9 | O12: =_xlfn.XLOOKUP(B12,DataSet!$N$2:$N$600,DataSet!$S$2:$S$600,0) -> 5 | P12: =_xlfn.XLOOKUP(B12,DataSet!$N$2:$N$600,DataSet!$T$2:$T$600,0) -> 0 | Q12: =_xlfn.XLOOKUP(B12,DataSet!$N$2:$N$600,DataSet!$U$2:$U$600,0) -> 34.47 | R12: =_xlfn.XLOOKUP(B12,DataSet!$N$2:$N$600,DataSet!$AB$2:$AB$600,0) -> 574.5 | S12: =_xlfn.XLOOKUP(B12,DataSet!$N$2:$N$600,DataSet!$AC$2:$AC$600,0) -> 574.5
A13: 11 | B13: FUR-TA-10001539 | C13: =_xlfn.XLOOKUP(B13,DataSet!$N$2:$N$600,DataSet!$AF$2:$AF$600,0) -> 115812 | D13: =_xlfn.XLOOKUP(B13,DataSet!$N$2:$N$600,DataSet!$G$2:$G$600,0) -> Brosina Hoffman | E13: =_xlfn.XLOOKUP(B13,DataSet!$N$2:$N$600,DataSet!$F$2:$F$600,0) -> BH-11710 | F13: =_xlfn.XLOOKUP(B13,DataSet!$N$2:$N$600,DataSet!$W$2:$W$600,0) -> Consumer | G13: =_xlfn.XLOOKUP(B13,DataSet!$N$2:$N$600,DataSet!$C$2:$C$600,0) -> 41799 | H13: =_xlfn.XLOOKUP(B13,DataSet!$N$2:$N$600,DataSet!$I$2:$I$600,0) -> United States | I13: =_xlfn.XLOOKUP(B13,DataSet!$N$2:$N$600,DataSet!$X$2:$X$600,0) -> Los Angeles - California | J13: =_xlfn.XLOOKUP(B13,DataSet!$N$2:$N$600,DataSet!$M$2:$M$600,0) -> West | K13: =_xlfn.XLOOKUP(B13,DataSet!$N$2:$N$600,DataSet!$O$2:$O$600,0) -> Furniture | L13: =_xlfn.XLOOKUP(B13,DataSet!$N$2:$N$600,DataSet!$Y$2:$Y$600,0) -> Tables | M13: =_xlfn.XLOOKUP(B13,DataSet!$N$2:$N$600,DataSet!$Q$2:$Q$600,0) -> Chromcraft Rectangular Conference Tables | N13: =_xlfn.XLOOKUP(B13,DataSet!$N$2:$N$600,DataSet!$AA$2:$AA$600,0) -> 1706.184 | O13: =_xlfn.XLOOKUP(B13,DataSet!$N$2:$N$600,DataSet!$S$2:$S$600,0) -> 9 | P13: =_xlfn.XLOOKUP(B13,DataSet!$N$2:$N$600,DataSet!$T$2:$T$600,0) -> 0.2 | Q13: =_xlfn.XLOOKUP(B13,DataSet!$N$2:$N$600,DataSet!$U$2:$U$600,0) -> 85.3092 | R13: =_xlfn.XLOOKUP(B13,DataSet!$N$2:$N$600,DataSet!$AB$2:$AB$600,0) -> 15355.656 | S13: =_xlfn.XLOOKUP(B13,DataSet!$N$2:$N$600,DataSet!$AC$2:$AC$600,0) -> 12284.525
A14: 12 | B14: TEC-PH-10002033 | C14: =_xlfn.XLOOKUP(B14,DataSet!$N$2:$N$600,DataSet!$AF$2:$AF$600,0) -> 115812 | D14: =_xlfn.XLOOKUP(B14,DataSet!$N$2:$N$600,DataSet!$G$2:$G$600,0) -> Brosina Hoffman | E14: =_xlfn.XLOOKUP(B14,DataSet!$N$2:$N$600,DataSet!$F$2:$F$600,0) -> BH-11710 | F14: =_xlfn.XLOOKUP(B14,DataSet!$N$2:$N$600,DataSet!$W$2:$W$600,0) -> Consumer | G14: =_xlfn.XLOOKUP(B14,DataSet!$N$2:$N$600,DataSet!$C$2:$C$600,0) -> 41799 | H14: =_xlfn.XLOOKUP(B14,DataSet!$N$2:$N$600,DataSet!$I$2:$I$600,0) -> United States | I14: =_xlfn.XLOOKUP(B14,DataSet!$N$2:$N$600,DataSet!$X$2:$X$600,0) -> Los Angeles - California | J14: =_xlfn.XLOOKUP(B14,DataSet!$N$2:$N$600,DataSet!$M$2:$M$600,0) -> West | K14: =_xlfn.XLOOKUP(B14,DataSet!$N$2:$N$600,DataSet!$O$2:$O$600,0) -> Technology | L14: =_xlfn.XLOOKUP(B14,DataSet!$N$2:$N$600,DataSet!$Y$2:$Y$600,0) -> Phones | M14: =_xlfn.XLOOKUP(B14,DataSet!$N$2:$N$600,DataSet!$Q$2:$Q$600,0) -> Konftel 250 Conference phone - Charcoal black | N14: =_xlfn.XLOOKUP(B14,DataSet!$N$2:$N$600,DataSet!$AA$2:$AA$600,0) -> 911.424 | O14: =_xlfn.XLOOKUP(B14,DataSet!$N$2:$N$600,DataSet!$S$2:$S$600,0) -> 4 | P14: =_xlfn.XLOOKUP(B14,DataSet!$N$2:$N$600,DataSet!$T$2:$T$600,0) -> 0.2 | Q14: =_xlfn.XLOOKUP(B14,DataSet!$N$2:$N$600,DataSet!$U$2:$U$600,0) -> 68.3568 | R14: =_xlfn.XLOOKUP(B14,DataSet!$N$2:$N$600,DataSet!$AB$2:$AB$600,0) -> 3645.696 | S14: =_xlfn.XLOOKUP(B14,DataSet!$N$2:$N$600,DataSet!$AC$2:$AC$600,0) -> 2916.5568
... A601: 599 | B601: OFF-SU-10004115 | C601: =_xlfn.XLOOKUP(B601,DataSet!$N$2:$N$600,DataSet!$AF$2:$AF$600,0) -> 120180 | D601: =_xlfn.XLOOKUP(B601,DataSet!$N$2:$N$600,DataSet!$G$2:$G$600,0) -> Theone Pippenger | E601: =_xlfn.XLOOKUP(B601,DataSet!$N$2:$N$600,DataSet!$F$2:$F$600,0) -> TP-21130 | F601: =_xlfn.XLOOKUP(B601,DataSet!$N$2:$N$600,DataSet!$W$2:$W$600,0) -> Consumer | G601: =_xlfn.XLOOKUP(B601,DataSet!$N$2:$N$600,DataSet!$C$2:$C$600,0) -> 42565 | H601: =_xlfn.XLOOKUP(B601,DataSet!$N$2:$N$600,DataSet!$I$2:$I$600,0) -> United States | I601: =_xlfn.XLOOKUP(B601,DataSet!$N$2:$N$600,DataSet!$X$2:$X$600,0) -> Philadelphia - Pennsylvania | J601: =_xlfn.XLOOKUP(B601,DataSet!$N$2:$N$600,DataSet!$M$2:$M$600,0) -> East | K601: =_xlfn.XLOOKUP(B601,DataSet!$N$2:$N$600,DataSet!$O$2:$O$600,0) -> Office Supplies | L601: =_xlfn.XLOOKUP(B601,DataSet!$N$2:$N$600,DataSet!$Y$2:$Y$600,0) -> Supplies | M601: =_xlfn.XLOOKUP(B601,DataSet!$N$2:$N$600,DataSet!$Q$2:$Q$600,0) -> Acme Stainless Steel Office Snips | N601: =_xlfn.XLOOKUP(B601,DataSet!$N$2:$N$600,DataSet!$AA$2:$AA$600,0) -> 11.632 | O601: =_xlfn.XLOOKUP(B601,DataSet!$N$2:$N$600,DataSet!$S$2:$S$600,0) -> 2 | P601: =_xlfn.XLOOKUP(B601,DataSet!$N$2:$N$600,DataSet!$T$2:$T$600,0) -> 0.2 | Q601: =_xlfn.XLOOKUP(B601,DataSet!$N$2:$N$600,DataSet!$U$2:$U$600,0) -> 1.0178 | R601: =_xlfn.XLOOKUP(B601,DataSet!$N$2:$N$600,DataSet!$AB$2:$AB$600,0) -> 23.264 | S601: =_xlfn.XLOOKUP(B601,DataSet!$N$2:$N$600,DataSet!$AC$2:$AC$600,0) -> 18.6112
